Workbook

Sheet Questão 1 - Multicolinearidade
B2: Insira seu nome e RA abaixo | D2: Escola Superior de Administração, Marketing e Comunicação (ESAMC) 10175/A - Econometria - 1º Sem. de 2021 - Prof. Pier Francesco De Maria | P2: Você recebeu os dados abaixo, relativos ao número de viagens de ônibus (Y, em milhares de passageiros por hora), à tarifa do ônibus (X1, em R$) e ao preço do litro da gasolina (X2, em R$). Faça o que é pedido abaixo, na ordem.
B4: 101190648 | P4: 1) (2.00 pontos) Estime o modelo de regressão Y = α + β1X1 + β2X2 + e, por meio do método de MQO. Interprete os resultados.
D5: Prova 2 / Parte 1 (Multicolinearidade) | P5: 2) (1.50 pontos) Avalie se o modelo como um todo é significativo (teste-F), construindo a tabela ANOVA.
B6: Este exercício vale 17,5% (dezessete porcento e cinco décimos) da nota da P2. A nota desta prova será ponderada junto às demais notas da Prova 2, compondo a nota da P2. Faça o que é pedido, sempre utilizando (a não ser que seja solicitado o contrário) álgebra matricial. Deixe todas as fórmulas indicadas, sob pena de perder nota! Você recebeu essa prova em 07/05, durante a aula. Faça a QUESTÃO 1 e devolva-a até 14/05, antes do horário da aula (19h30). Ao terminar a sua prova, SALVE O ARQUIVO E ENVIE PARA O E-MAIL pier.francesco@esamc.br! | P6: 3) (2.00 pontos) Avalie se, isoladamente, os coeficientes do modelo são significativos, por meio do teste-T.
P7: 4) (2.00 pontos) Calcule os FIV para X1 e X2. Avalie se, a partir dos mesmos, é possível concluir pela multicolinearidade (SE SIM, INDIQUE QUAL(IS) VARIÁVEL(IS).
P8: 5) (1.50 pontos) Escolha sabiamente uma variável para converter em logaritmo. Depois, re-faça e re-interprete o modelo por MQO.
P9: 6) (1.00 pontos) O que você sugere fazer, diante das evidências encontradas?
P12: Y | Q12: X1 | R12: X2
P13: 2073 | Q13: 0.85 | R13: 0.88
P14: 2136 | Q14: 0.75 | R14: 1.03
P15: 1879 | Q15: 0.6 | R15: 0.91
P16: 938 | Q16: 1 | R16: 0.91
P17: 7343 | Q17: 0.5 | R17: 0.97
P18: 838 | Q18: 0.85 | R18: 0.88
P19: 1648 | Q19: 1 | R19: 0.91
P20: 739 | Q20: 0.75 | R20: 0.89
P21: 1071 | Q21: 1.5 | R21: 0.89
P22: 275 | Q22: 1.5 | R22: 0.89

Sheet Questão 2 - Heterocedasticidade
B2: Insira seu nome e RA abaixo | D2: Escola Superior de Administração, Marketing e Comunicação (ESAMC) 10175/A - Econometria - 1º Sem. de 2021 - Prof. Pier Francesco De Maria | P2: Você recebeu os dados abaixo, relativos ao investimento de empresas (I, em US$ mi), seus valores em ações (V, em US$ mi) e o valor de capital da firma (K, em US$ mi). Faça o que é pedido abaixo, na ordem.
B4: 101190648 | P4: 1) (1.00 pontos) Estime o modelo de regressão I = α + β1V + β2K + e, por meio do método de MQO. Interprete os resultados.
D5: Prova 2 / Parte 2 (Heterocedasticidade) | P5: 2) (1.00 pontos) Construa a tabela ANOVA (e interprete o teste-F), calcule o R² ajustado e avalie a significância dos coeficientes (teste-T).
B6: Este exercício vale 17,5% (dezessete porcento e cinco décimos) da nota da P2. A nota desta prova será ponderada junto às demais notas da Prova 2, compondo a nota da P2. Faça o que é pedido, sempre utilizando (a não ser que seja solicitado o contrário) álgebra matricial. Deixe todas as fórmulas indicadas, sob pena de perder nota! Você recebeu essa prova em 07/05, durante a aula. Faça a QUESTÃO 2 e devolva-a até 21/05, antes do horário da aula (19h30). Ao terminar a sua prova, SALVE O ARQUIVO E ENVIE PARA O E-MAIL pier.francesco@esamc.br! | P6: 3) (1.50 pontos) Realize a avaliação gráfica e conclua se há ou não suspeita de heterocedasticidade.
P7: 4) (2.00 pontos) Realize o teste de Breusch-Pagan e o teste de White. O que você conclui, a partir dos resultados?
P8: 5) (2.00 pontos) Aplique o método dos MQGF e obtenha os novos estimadores da regressão. Compare resultados com o item (1).
P9: 6) (1.50 pontos) Escolha sabiamente uma variável para converter em logaritmo. Avalie se, após fazer MQO, ainda persiste a heterocedasticidade.
P10: 7) (1.00 pontos) O que você consegue concluir, diante das evidências encontradas?
P12: I | Q12: V | R12: K
P13: 33.1 | Q13: 1170.6 | R13: 97.8
P14: 80 | Q14: 1588 | R14: 287.8
P15: 67 | Q15: 1687.2 | R15: 321.3
P16: 82 | Q16: 1749.4 | R16: 319.9
P17: 72 | Q17: 1834.1 | R17: 220.9
P18: 45 | Q18: 2015.8 | R18: 104.4
P19: 44.6 | Q19: 2039.7 | R19: 156.2
P20: 98 | Q20: 2132.2 | R20: 186.6

Sheet RESOLUÇÃO QUESTÃO 1
A1: Y | C1: X1 | D1: X2 | F1: 1 | G1: 1 | H1: 1 | I1: 1 | J1: 1 | K1: 1 | L1: 1 | M1: 1 | N1: 1 | O1: 1
A2: 2073 | B2: 1 | C2: 0.85 | D2: 0.88 | F2: 0.85 | G2: 0.75 | H2: 0.6 | I2: 1 | J2: 0.5 | K2: 0.85 | L2: 1 | M2: 0.75 | N2: 1.5 | O2: 1.5 | V2: RESUMO DOS RESULTADOS
A3: 2136 | B3: 1 | C3: 0.75 | D3: 1.03 | F3: 0.88 | G3: 1.03 | H3: 0.91 | I3: 0.91 | J3: 0.97 | K3: 0.88 | L3: 0.91 | M3: 0.89 | N3: 0.89 | O3: 0.89
A4: 1879 | B4: 1 | C4: 0.6 | D4: 0.91 | V4: Estatística de regressão
A5: 938 | B5: 1 | C5: 1 | D5: 0.91 | F5: {=MMULT(F1:O3,B2:D11)} -> 10 | G5: 9.3 | H5: 9.16 | J5: {=MINVERSE(F5:H7)} -> 56.696603 | K5: -4.3414316 | L5: -57.378899 | N5: {=MMULT(F1:O3,A2:A11)} -> 18940 | O5: 18940 | P5: 18940 | V5: R múltiplo | W5: 0.65831616
A6: 7343 | B6: 1 | C6: 0.5 | D6: 0.97 | F6: 9.3 | G6: 9.68 | H6: 8.457 | J6: -4.3414316 | K6: 1.18209 | L6: 3.5393973 | N6: 14034.5 | O6: 14034.5 | P6: 14034.5 | V6: R-Quadrado | W6: 0.43338017
A7: 838 | B7: 1 | C7: 0.85 | D7: 0.88 | F7: 9.16 | G7: 8.457 | H7: 8.4112 | J7: -57.378899 | K7: 3.5393973 | L7: 59.047226 | N7: 17803.27 | O7: 17803.27 | P7: 17803.27 | V7: R-quadrado ajustado | W7: 0.27148879
A8: 1648 | B8: 1 | C8: 1 | D8: 0.91 | V8: Erro padrão | W8: 1718.9778
A9: 739 | B9: 1 | C9: 0.75 | D9: 0.89 | F9: α | G9: {=MMULT(J5:L7,N5:P7)} -> -8628.1946 | I9: n | J9: ybarra | L9: yTy | M9: βTXTy | V9: Observações | W9: 10
A10: 1071 | B10: 1 | C10: 1.5 | D10: 0.89 | F10: β1 | G10: -2623.827 | I10: =COUNT(A2:A11) -> 10 | J10: =AVERAGE(A2:A11) -> 1894 | L10: {=MMULT(TRANSPOSE(A2:A11),A2:A11)} -> 72376894 | M10: {=MMULT(TRANSPOSE(G9:G11),MMULT(F1:O3,A2:A11))} -> 51692701
A11: 275 | B11: 1 | C11: 1.5 | D11: 0.89 | F11: β2 | G11: 14151.041 | V11: ANOVA
W12: gl | X12: SQ | Y12: MQ | Z12: F | AA12: F de significação
F13: STQ | G13: =L10-I10*J10^2 -> 36504534 | J13: TABELA ANOVA | V13: Regressão | W13: 2 | X13: 15820341 | Y13: 7910170.5 | Z13: 2.6769811 | AA13: 0.13693712
A14: Interpretação do modelo | F14: SQReg | G14: =M10-I10*J10^2 -> 15820341 | J14: Fonte | K14: GL | L14: SQ | M14: QM | N14: F(calc) | O14: F(crit) | Q14: O modelo como um todo é significante. Ou seja, rejeitamos H0, pois F(calc) é maior do que F(crit). | V14: Resíduo | W14: 7 | X14: 20684193 | Y14: 2954884.7
A15: Y = -8628,1947 -2623,8271*X1 +14151,05*X2 + e | F15: SQRes | G15: =L10-M10 -> 20684193 | J15: Regressão | K15: 2 | L15: =G14 -> 15820341 | M15: =L15/K15 -> 7910170.5 | N15: =M15/M16 -> 2.6769811 | O15: =_xlfn.F.INV(5%,K15,K16) -> 0.051670995 | V15: Total | W15: 9 | X15: 36504534
A16: A cada 1 p.p de aumento em X1 há dimunuição de 2623,83 em Y | F16: Resultado | G16: =G14+G15=G13 -> TRUE | J16: Resíduos | K16: =I10-(K15+1) -> 7 | L16: =G15 -> 20684193 | M16: =L16/K16 -> 2954884.7
A17: A cada 1 p.p de aumento em X2 há aumento de 14151,05 em Y | F17: R² | G17: =G14/G13 -> 0.43338017 | J17: Total | K17: =I10-1 -> 9 | L17: =G13 -> 36504534 | M17: =L17/K17 -> 4056059.3 | W17: Coeficientes | X17: Erro padrão | Y17: Stat t | Z17: valor-P | AA17: 95% inferiores | AB17: 95% superiores | AC17: Inferior 95,0% | AD17: Superior 95,0%
F18: R² ajustado | G18: =1-(M16/M17) -> 0.27148879 | V18: Interseção | W18: -8628.1946 | X18: 12943.412 | Y18: -0.66660896 | Z18: 0.52637542 | AA18: -39234.501 | AB18: 21978.112 | AC18: -39234.501 | AD18: 21978.112
J19: Matriz VAR-COVAR | V19: X1 | W19: -2623.827 | X19: 1868.9408 | Y19: -1.4039113 | Z19: 0.20312186 | AA19: -7043.1697 | AB19: 1795.5156 | AC19: -7043.1697 | AD19: 1795.5156
F20: Sigma^² | G20: =(G13-G14)/K16 -> 2954884.7 | J20: {=J5:L7*G20} -> 1.6753192e+08 | K20: -12828430 | L20: -1.6954803e+08 | V20: X2 | W20: 14151.041 | X20: 13209.002 | Y20: 1.0713179 | Z20: 0.31956746 | AA20: -17083.286 | AB20: 45385.369 | AC20: -17083.286 | AD20: 45385.369
J21: -12828430 | K21: 3492939.6 | L21: 10458511
J22: -1.6954803e+08 | K22: 10458511 | L22: 1.7447775e+08
K24: α | L24: β1 | M24: β2
K25: -8628.1946 | L25: -2623.827 | M25: 14151.041
J26: t(calc) | K26: =K25/SQRT(J20) -> -0.66660896 | L26: =L25/SQRT(K21) -> -1.4039113 | M26: =M25/SQRT(L22) -> 1.0713179 | O26: β2 é significativo. Apenas β1 não é siginficativo isoladamente, portanto não rejeitamos H0 para ele.
J27: t(crit) | K27: =_xlfn.T.INV(5%,K16) -> -1.8945786
A30: Y (X1) | C30: X2 | E30: 1 | F30: 1 | G30: 1 | H30: 1 | I30: 1 | J30: 1 | K30: 1 | L30: 1 | M30: 1 | N30: 1 | V30: RESUMO DOS RESULTADOS
A31: 0.85 | B31: 1 | C31: 0.88 | E31: 0.88 | F31: 1.03 | G31: 0.91 | H31: 0.91 | I31: 0.97 | J31: 0.88 | K31: 0.91 | L31: 0.89 | M31: 0.89 | N31: 0.89
A32: 0.75 | B32: 1 | C32: 1.03 | V32: Estatística de regressão
A33: 0.6 | B33: 1 | C33: 0.91 | E33: {=MMULT(E30:N31,B31:C40)} -> 10 | F33: 9.16 | H33: {=MINVERSE(E33:F34)} -> 40.751938 | I33: -44.379845 | K33: {=MMULT(E30:N31,A31:A40)} -> 9.3 | L33: 9.3 | V33: R múltiplo | W33: 0.42364716
A34: 1 | B34: 1 | C34: 0.91 | E34: 9.16 | F34: 8.4112 | H34: -44.379845 | I34: 48.449612 | K34: 8.457 | L34: 8.457 | V34: R-Quadrado | W34: 0.17947691
A35: 0.5 | B35: 1 | C35: 0.97 | V35: R-quadrado ajustado | W35: 0.076911528
A36: 0.85 | B36: 1 | C36: 0.88 | E36: α | F36: {=MMULT(H33:I34,K33:L34)} -> 3.6726744 | H36: n | I36: ybarra | K36: yTy | L36: βTXTy | V36: Erro padrão | W36: 0.32518443
A37: 1 | B37: 1 | C37: 0.91 | E37: β1 | F37: -2.994186 | H37: =COUNT(A31:A40) -> 10 | I37: =AVERAGE(A31:A40) -> 0.93 | K37: {=MMULT(TRANSPOSE(A31:A40),A31:A40)} -> 9.68 | L37: {=MMULT(TRANSPOSE(F36:F37),MMULT(E30:N31,A31:A40))} -> 8.8340407 | V37: Observações | W37: 10
A38: 0.75 | B38: 1 | C38: 0.89
A39: 1.5 | B39: 1 | C39: 0.89 | E39: STQ | F39: =K37-H37*I37^2 -> 1.031 | V39: ANOVA
A40: 1.5 | B40: 1 | C40: 0.89 | E40: SQReg | F40: =L37-H37*I37^2 -> 0.1850407 | W40: gl | X40: SQ | Y40: MQ | Z40: F | AA40: F de significação
E41: SQRes | F41: =K37-L37 -> 0.8459593 | V41: Regressão | W41: 1 | X41: 0.1850407 | Y41: 0.1850407 | Z41: 1.749878 | AA41: 0.2224525
E42: Resultado | F42: =F40+F41=F39 -> TRUE | V42: Resíduo | W42: 8 | X42: 0.8459593 | Y42: 0.10574491
E43: R² | F43: =F40/F39 -> 0.17947691 | V43: Total | W43: 9 | X43: 1.031
E45: FIV | F45: =1/(1-F43) -> 1.2187348 | H45: Não temos multicolinearidade pois o resultado do FIV não é > 10 | W45: Coeficientes | X45: Erro padrão | Y45: Stat t | Z45: valor-P | AA45: 95% inferiores | AB45: 95% superiores | AC45: Inferior 95,0% | AD45: Superior 95,0%
V46: Interseção | W46: 3.6726744 | X46: 2.0758878 | Y46: 1.7692066 | Z46: 0.1148249 | AA46: -1.1143314 | AB46: 8.4596803 | AC46: -1.1143314 | AD46: 8.4596803
V47: X2 | W47: -2.994186 | X47: 2.2634708 | Y47: -1.3228295 | Z47: 0.2224525 | AA47: -8.2137591 | AB47: 2.225387 | AC47: -8.2137591 | AD47: 2.225387
A51: Y (X2) | C51: X1 | E51: 1 | F51: 1 | G51: 1 | H51: 1 | I51: 1 | J51: 1 | K51: 1 | L51: 1 | M51: 1 | N51: 1 | V51: RESUMO DOS RESULTADOS
A52: 0.88 | B52: 1 | C52: 0.85 | E52: 0.85 | F52: 0.75 | G52: 0.6 | H52: 1 | I52: 0.5 | J52: 0.85 | K52: 1 | L52: 0.75 | M52: 1.5 | N52: 1.5
A53: 1.03 | B53: 1 | C53: 0.75 | V53: Estatística de regressão
A54: 0.91 | B54: 1 | C54: 0.6 | E54: {=MMULT(E51:N52,B52:C61)} -> 10 | F54: 9.3 | H54: {=MINVERSE(E54:F55)} -> 0.93889428 | I54: -0.90203686 | K54: {=MMULT(E51:N52,A52:A61)} -> 9.16 | L54: 9.16 | V54: R múltiplo | W54: 0.42364716
A55: 0.91 | B55: 1 | C55: 1 | E55: 9.3 | F55: 9.68 | H55: -0.90203686 | I55: 0.9699321 | K55: 8.457 | L55: 8.457 | V55: R-Quadrado | W55: 0.17947691
A56: 0.97 | B56: 1 | C56: 0.5 | V56: R-quadrado ajustado | W56: 0.076911528
A57: 0.88 | B57: 1 | C57: 0.85 | E57: α | F57: {=MMULT(H54:I55,K54:L55)} -> 0.97174588 | H57: n | I57: ybarra | K57: yTy | L57: βTXTy | V57: Erro padrão | W57: 0.04601032
A58: 0.91 | B58: 1 | C58: 1 | E58: β1 | F58: -0.059941804 | H58: =COUNT(A52:A61) -> 10 | I58: =AVERAGE(A52:A61) -> 0.916 | K58: {=MMULT(TRANSPOSE(A52:A61),A52:A61)} -> 8.4112 | L58: {=MMULT(TRANSPOSE(F57:F58),MMULT(E51:N52,A52:A61))} -> 8.3942644 | V58: Observações | W58: 10
A59: 0.89 | B59: 1 | C59: 0.75
A60: 0.89 | B60: 1 | C60: 1.5 | E60: STQ | F60: =K58-H58*I58^2 -> 0.02064 | V60: ANOVA
A61: 0.89 | B61: 1 | C61: 1.5 | E61: SQReg | F61: =L58-H58*I58^2 -> 0.0037044035 | W61: gl | X61: SQ | Y61: MQ | Z61: F | AA61: F de significação
E62: SQRes | F62: =K58-L58 -> 0.016935597 | V62: Regressão | W62: 1 | X62: 0.0037044035 | Y62: 0.0037044035 | Z62: 1.749878 | AA62: 0.2224525
E63: Resultado | F63: =F61+F62=F60 -> TRUE | V63: Resíduo | W63: 8 | X63: 0.016935597 | Y63: 0.0021169496
E64: R² | F64: =F61/F60 -> 0.17947691 | V64: Total | W64: 9 | X64: 0.02064
E66: FIV | F66: =1/(1-F64) -> 1.2187348 | H66: Não temos multicolinearidade pois o resultado do FIV não é > 10 | W66: Coeficientes | X66: Erro padrão | Y66: Stat t | Z66: valor-P | AA66: 95% inferiores | AB66: 95% superiores | AC66: Inferior 95,0% | AD66: Superior 95,0%
V67: Interseção | W67: 0.97174588 | X67: 0.044582416 | Y67: 21.796618 | Z67: 2.0701123e-08 | AA67: 0.86893864 | AB67: 1.0745531 | AC67: 0.86893864 | AD67: 1.0745531
A69: Y | C69: X1 | D69: X2(log) | F69: 1 | G69: 1 | H69: 1 | I69: 1 | J69: 1 | K69: 1 | L69: 1 | M69: 1 | N69: 1 | O69: 1 | S69: RESUMO DOS RESULTADOS
A70: 2073 | B70: 1 | C70: 0.85 | D70: =ROW(D2) -> 2 | F70: 0.85 | G70: 0.75 | H70: 0.6 | I70: 1 | J70: 0.5 | K70: 0.85 | L70: 1 | M70: 0.75 | N70: 1.5 | O70: 1.5
A71: 2136 | B71: 1 | C71: 0.75 | D71: =ROW(D3) -> 3 | F71: 2 | G71: 3 | H71: 4 | I71: 5 | J71: 6 | K71: 7 | L71: 8 | M71: 9 | N71: 10 | O71: 11 | S71: Estatística de regressão
A72: 1879 | B72: 1 | C72: 0.6 | D72: =ROW(D4) -> 4 | S72: R múltiplo | T72: 0.59288388
A73: 938 | B73: 1 | C73: 1 | D73: =ROW(D5) -> 5 | F73: {=MMULT(F69:O71,B70:D79)} -> 10 | G73: 9.3 | H73: 65 | J73: {=MINVERSE(F73:H75)} -> 0.96033753 | K73: -0.77485762 | L73: -0.021495376 | N73: {=MMULT(F69:O71,A70:A79)} -> 18940 | O73: 18940 | P73: 18940 | S73: R-Quadrado | T73: 0.35151129
A74: 7343 | B74: 1 | C74: 0.5 | D74: =ROW(D6) -> 6 | F74: 9.3 | G74: 9.68 | H74: 66.55 | J74: -0.77485762 | K74: 1.724228 | L74: -0.12748837 | N74: 14034.5 | O74: 14034.5 | P74: 14034.5 | S74: R-quadrado ajustado | T74: 0.1662288
A75: 838 | B75: 1 | C75: 0.85 | D75: =ROW(D7) -> 7 | F75: 65 | G75: 66.55 | H75: 505 | J75: -0.021495376 | K75: -0.12748837 | L75: 0.021547625 | N75: 106254 | O75: 106254 | P75: 106254 | S75: Erro padrão | T75: 1838.974
A76: 1648 | B76: 1 | C76: 1 | D76: =ROW(D8) -> 8 | S76: Observações | T76: 10
A77: 739 | B77: 1 | C77: 0.75 | D77: =ROW(D9) -> 9 | F77: α | G77: {=MMULT(J73:L75,N73:P75)} -> 5030.0839 | I77: n | J77: ybarra | L77: yTy | M77: βTXTy
A78: 1071 | B78: 1 | C78: 1.5 | D78: =ROW(D10) -> 10 | F78: β1 | G78: -4023.275 | I78: =COUNT(A70:A79) -> 10 | J78: =AVERAGE(A70:A79) -> 1894 | L78: {=MMULT(TRANSPOSE(A70:A79),A70:A79)} -> 72376894 | M78: {=MMULT(TRANSPOSE(G77:G79),MMULT(F69:O71,A70:A79))} -> 48704116 | S78: ANOVA
A79: 275 | B79: 1 | C79: 1.5 | D79: =ROW(D11) -> 11 | F79: β2 | G79: 93.163363 | T79: gl | U79: SQ | V79: MQ | W79: F | X79: F de significação
S80: Regressão | T80: 2 | U80: 12831756 | V80: 6415877.9 | W80: 1.8971641 | X80: 0.21961321
F81: STQ | G81: =L78-I78*J78^2 -> 36504534 | J81: TABELA ANOVA | S81: Resíduo | T81: 7 | U81: 23672778 | V81: 3381825.5
A82: A variável X2 foi escolhida para ser transformada em logaritmo já que X1 e X2 são muito parecidas, porém de acordo com os resuldados do R² ajustado, o modelo se tornou menos significativo. | F82: SQReg | G82: =M78-I78*J78^2 -> 12831756 | J82: Fonte | K82: GL | L82: SQ | M82: QM | N82: F(calc) | O82: F(crit) | S82: Total | T82: 9 | U82: 36504534
F83: SQRes | G83: =L78-M78 -> 23672778 | J83: Regressão | K83: 2 | L83: =G82 -> 12831756 | M83: =L83/K83 -> 6415877.9 | N83: =M83/M84 -> 1.8971641 | O83: =_xlfn.F.INV(5%,K83,K84) -> 0.051670995
F84: Resultado | G84: =G82+G83=G81 -> TRUE | J84: Resíduos | K84: =I78-(K83+1) -> 7 | L84: =G83 -> 23672778 | M84: =L84/K84 -> 3381825.5 | T84: Coeficientes | U84: Erro padrão | V84: Stat t | W84: valor-P | X84: 95% inferiores | Y84: 95% superiores | Z84: Inferior 95,0% | AA84: Superior 95,0%
F85: R² | G85: =G82/G81 -> 0.35151129 | J85: Total | K85: =I78-1 -> 9 | L85: =G81 -> 36504534 | M85: =L85/K85 -> 4056059.3 | S85: Interseção | T85: 5030.0839 | U85: 1802.1359 | V85: 2.791179 | W85: 0.026862746 | X85: 768.70956 | Y85: 9291.4582 | Z85: 768.70956 | AA85: 9291.4582
F86: R² ajustado | G86: =1-(M84/M85) -> 0.1662288 | S86: X1 | T86: -4023.275 | U86: 2414.7543 | V86: -1.6661219 | W86: 0.13962981 | X86: -9733.2615 | Y86: 1686.7115 | Z86: -9733.2615 | AA86: 1686.7115
S87: X2(log) | T87: 93.163363 | U87: 269.94501 | V87: 0.34511978 | W87: 0.74014226 | X87: -545.15515 | Y87: 731.48188 | Z87: -545.15515 | AA87: 731.48188
A89: Para resolução deste case, indicaria trocar uma das variáveis para algo que tenha mais inferência no modelo, já que as duas são muito parecidas, e claro, adicionar mais amostras para serem calculadas com maior precisão nosso modelo de regressão multipla.

Sheet RESOLUÇÃO QUESTÃO 2
A1: I(y) | C1: V(X1) | D1: K(X2) | E1: ê | F1: ê^2 | H1: 1 | I1: 1 | J1: 1 | K1: 1 | L1: 1 | M1: 1 | N1: 1 | O1: 1 | X1: RESUMO DOS RESULTADOS
A2: 33.1 | B2: 1 | C2: 1170.6 | D2: 97.8 | E2: {=A2-($M$9+SUMPRODUCT(TRANSPOSE($M$10:$M$11),C2:D2))} -> 3.9343507 | F2: =E2^2 -> 15.479116 | H2: 1170.6 | I2: 1588 | J2: 1687.2 | K2: 1749.4 | L2: 1834.1 | M2: 2015.8 | N2: 2039.7 | O2: 2132.2
A3: 80 | B3: 1 | C3: 1588 | D3: 287.8 | E3: {=A3-($M$9+SUMPRODUCT(TRANSPOSE($M$10:$M$11),C3:D3))} -> 7.6233093 | F3: =E3^2 -> 58.114844 | H3: 97.8 | I3: 287.8 | J3: 321.3 | K3: 319.9 | L3: 220.9 | M3: 104.4 | N3: 156.2 | O3: 186.6 | X3: Estatística de regressão
A4: 67 | B4: 1 | C4: 1687.2 | D4: 321.3 | E4: {=A4-($M$9+SUMPRODUCT(TRANSPOSE($M$10:$M$11),C4:D4))} -> -13.722475 | F4: =E4^2 -> 188.30633 | X4: R múltiplo | Y4: 0.76639439
A5: 82 | B5: 1 | C5: 1749.4 | D5: 319.9 | E5: {=A5-($M$9+SUMPRODUCT(TRANSPOSE($M$10:$M$11),C5:D5))} -> -0.25737217 | F5: =E5^2 -> 0.066240431 | H5: {=MMULT(H1:O3,B2:D9)} -> 8 | I5: 14217 | J5: 1694.9 | L5: {=MINVERSE(H5:J7)} -> 5.7694577 | M5: -0.0027015923 | N5: -0.0039808393 | X5: R-Quadrado | Y5: 0.58736036
A6: 72 | B6: 1 | C6: 1834.1 | D6: 220.9 | E6: {=A6-($M$9+SUMPRODUCT(TRANSPOSE($M$10:$M$11),C6:D6))} -> 3.6781979 | F6: =E6^2 -> 13.52914 | H6: 14217 | I6: 25933118 | J6: 3005313.4 | L6: -0.0027015923 | M6: 1.4993701e-06 | N6: 1.7475569e-07 | X6: R-quadrado ajustado | Y6: 0.42230451
A7: 45 | B7: 1 | C7: 2015.8 | D7: 104.4 | E7: {=A7-($M$9+SUMPRODUCT(TRANSPOSE($M$10:$M$11),C7:D7))} -> -9.2517936 | F7: =E7^2 -> 85.595684 | H7: 1694.9 | I7: 3005313.4 | J7: 416877.55 | L7: -0.0039808393 | M7: 1.7475569e-07 | N7: 1.7323862e-05 | X7: Erro padrão | Y7: 16.969787
A8: 44.6 | B8: 1 | C8: 2039.7 | D8: 156.2 | E8: {=A8-($M$9+SUMPRODUCT(TRANSPOSE($M$10:$M$11),C8:D8))} -> -18.880163 | F8: =E8^2 -> 356.46055 | X8: Observações | Y8: 8
A9: 98 | B9: 1 | C9: 2132.2 | D9: 186.6 | E9: {=A9-($M$9+SUMPRODUCT(TRANSPOSE($M$10:$M$11),C9:D9))} -> 26.875946 | F9: =E9^2 -> 722.31647 | H9: {=MMULT(H1:O3,A2:A9)} -> 521.7 | I9: 521.7 | J9: 521.7 | L9: α | M9: {=MMULT(L5:N7,H9:J11)} -> -20.212138 | O9: Y = -20,2121 +0,0283 *X1 + 0,16505*X2 + e
H10: 944972.48 | I10: 944972.48 | J10: 944972.48 | L10: β1 | M10: 0.028391845 | O10: A cada 1 p.p de aumento em X1 há aumento de 0,028392 em Y | X10: ANOVA
H11: 119876.2 | I11: 119876.2 | J11: 119876.2 | L11: β2 | M11: 0.16505413 | O11: A cada 1 p.p de aumento em X2 há aumento de 0,16505 em Y | Y11: gl | Z11: SQ | AA11: MQ | AB11: F | AC11: F de significação
X12: Regressão | Y12: 2 | Z12: 2049.5404 | AA12: 1024.7702 | AB12: 3.5585551 | AC12: 0.10937734
H13: n | I13: ybarra | K13: yTy | L13: βTXTy | X13: Resíduo | Y13: 5 | Z13: 1439.8684 | AA13: 287.97367
H14: =COUNT(A2:A9) -> 8 | I14: =AVERAGE(A2:A9) -> 65.2125 | K14: {=MMULT(TRANSPOSE(A2:A9),A2:A9)} -> 37510.77 | L14: {=MMULT(TRANSPOSE(M9:M11),MMULT(H1:O3,A2:A9))} -> 36070.902 | X14: Total | Y14: 7 | Z14: 3489.4088
H16: STQ | I16: =K14-H14*I14^2 -> 3489.4087 | K16: TABELA ANOVA | Y16: Coeficientes | Z16: Erro padrão | AA16: Stat t | AB16: valor-P | AC16: 95% inferiores | AD16: 95% superiores | AE16: Inferior 95,0% | AF16: Superior 95,0%
H17: SQReg | I17: =L14-H14*I14^2 -> 2049.5404 | K17: Fonte | L17: GL | M17: SQ | N17: QM | O17: F(calc) | P17: F(crit) | X17: Interseção | Y17: -20.212138 | Z17: 40.760912 | AA17: -0.49587061 | AB17: 0.64101027 | AC17: -124.9914 | AD17: 84.567121 | AE17: -124.9914 | AF17: 84.567121
H18: SQRes | I18: =K14-L14 -> 1439.8684 | K18: Regressão | L18: 2 | M18: =I17 -> 2049.5404 | N18: =M18/L18 -> 1024.7702 | O18: =N18/N19 -> 3.5585551 | P18: =_xlfn.F.INV(5%,L18,L19) -> 0.051823112 | R18: O modelo como um todo é significante. Ou seja, rejeitamos H0, pois F(calc) é maior do que F(crit). | X18: VX1) | Y18: 0.028391845 | Z18: 0.020779295 | AA18: 1.3663526 | AB18: 0.23006915 | AC18: -0.025023035 | AD18: 0.081806724 | AE18: -0.025023035 | AF18: 0.081806724
H19: Resultado | I19: =I17+I18=I16 -> TRUE | K19: Resíduos | L19: =H14-(L18+1) -> 5 | M19: =I18 -> 1439.8684 | N19: =M19/L19 -> 287.97367 | X19: K(X2) | Y19: 0.16505413 | Z19: 0.070631551 | AA19: 2.3368329 | AB19: 0.066642187 | AC19: -0.016510048 | AD19: 0.34661832 | AE19: -0.016510048 | AF19: 0.34661832
H20: R² | I20: =I17/I16 -> 0.58736036 | K20: Total | L20: =H14-1 -> 7 | M20: =I16 -> 3489.4087 | N20: =M20/L20 -> 498.48696
H21: R² ajustado | I21: =1-(N19/N20) -> 0.42230451
A24: De acordo com a análise gráfica, há heterocedasticidade em ambas variáveis X, pois a disperssão dos pontos não tem padrão horizontal.
A39: Para o teste Breusch-Pagan (BP) | X39: RESUMO DOS RESULTADOS
A40: ê^2(y) | C40: V(X1) | D40: K(X2) | F40: 1 | G40: 1 | H40: 1 | I40: 1 | J40: 1 | K40: 1 | L40: 1 | M40: 1
A41: =F2 -> 15.479116 | B41: 1 | C41: 1170.6 | D41: 97.8 | F41: 1170.6 | G41: 1588 | H41: 1687.2 | I41: 1749.4 | J41: 1834.1 | K41: 2015.8 | L41: 2039.7 | M41: 2132.2 | X41: Estatística de regressão
A42: =F3 -> 58.114844 | B42: 1 | C42: 1588 | D42: 287.8 | F42: 97.8 | G42: 287.8 | H42: 321.3 | I42: 319.9 | J42: 220.9 | K42: 104.4 | L42: 156.2 | M42: 186.6 | X42: R múltiplo | Y42: 0.63215796
A43: =F4 -> 188.30633 | B43: 1 | C43: 1687.2 | D43: 321.3 | X43: R-Quadrado | Y43: 0.39962369
A44: =F5 -> 0.066240431 | B44: 1 | C44: 1749.4 | D44: 319.9 | F44: {=MMULT(F40:M42,B41:D48)} -> 8 | G44: 14217 | H44: 1694.9 | J44: {=MINVERSE(F44:H46)} -> 5.7694577 | K44: -0.0027015923 | L44: -0.0039808393 | X44: R-quadrado ajustado | Y44: 0.15947316
A45: =F6 -> 13.52914 | B45: 1 | C45: 1834.1 | D45: 220.9 | F45: 14217 | G45: 25933118 | H45: 3005313.4 | J45: -0.0027015923 | K45: 1.4993701e-06 | L45: 1.7475569e-07 | X45: Erro padrão | Y45: 228.86994
A46: =F7 -> 85.595684 | B46: 1 | C46: 2015.8 | D46: 104.4 | F46: 1694.9 | G46: 3005313.4 | H46: 416877.55 | J46: -0.0039808393 | K46: 1.7475569e-07 | L46: 1.7323862e-05 | X46: Observações | Y46: 8
A47: =F8 -> 356.46055 | B47: 1 | C47: 2039.7 | D47: 156.2
A48: =F9 -> 722.31647 | B48: 1 | C48: 2132.2 | D48: 186.6 | F48: {=MMULT(F40:M42,A41:A48)} -> 1439.8684 | G48: 1439.8684 | H48: 1439.8684 | J48: γ | K48: {=MMULT(J44:L46,F48:H50)} -> -627.08716 | X48: ANOVA
F49: 2892785.9 | G49: 2892785.9 | H49: 2892785.9 | J49: δ1 | K49: 0.49655221 | Y49: gl | Z49: SQ | AA49: MQ | AB49: F | AC49: F de significação
F50: 281151.49 | G50: 281151.49 | H50: 281151.49 | J50: δ2 | K50: -0.35572434 | X50: Regressão | Y50: 2 | Z50: 174331.22 | AA50: 87165.611 | AB50: 1.664055 | AC50: 0.27929224
X51: Resíduo | Y51: 5 | Z51: 261907.24 | AA51: 52381.448
F52: n | G52: ybarra | H52: nYmédio² | I52: yTy | J52: βTXTy | X52: Total | Y52: 7 | Z52: 436238.46
F53: =COUNT(A41:A48) -> 8 | G53: =AVERAGE(A41:A48) -> 179.98355 | H53: =COUNTA(A41:A48)*AVERAGE(A41:A48)^2 -> 259152.61 | I53: {=MMULT(TRANSPOSE(A41:A48),A41:A48)} -> 695391.07 | J53: {=MMULT(TRANSPOSE(K48:K50),MMULT(F40:M42,A41:A48))} -> 433483.83
Y54: Coeficientes | Z54: Erro padrão | AA54: Stat t | AB54: valor-P | AC54: 95% inferiores | AD54: 95% superiores | AE54: Inferior 95,0% | AF54: Superior 95,0%
F55: STQ | G55: =I53-F53*G53^2 -> 436238.46 | I55: TABELA ANOVA | X55: Interseção | Y55: -627.08716 | Z55: 549.73862 | AA55: -1.1407006 | AB55: 0.30566848 | AC55: -2040.2353 | AD55: 786.06095 | AE55: -2040.2353 | AF55: 786.06095
F56: SQReg | G56: =J53-F53*G53^2 -> 174331.22 | I56: Fonte | J56: GL | K56: SQ | L56: QM | M56: F(calc) | N56: F(crit) | X56: V(X1) | Y56: 0.49655221 | Z56: 0.28024842 | AA56: 1.7718288 | AB56: 0.13662537 | AC56: -0.22384928 | AD56: 1.2169537 | AE56: -0.22384928 | AF56: 1.2169537
F57: SQRes | G57: =I53-J53 -> 261907.24 | I57: Regressão | J57: 2 | K57: =G56 -> 174331.22 | L57: =K57/J57 -> 87165.611 | M57: =L57/L58 -> 1.664055 | N57: =_xlfn.F.INV(5%,J57,J58) -> 0.051823112 | X57: K(X2) | Y57: -0.35572434 | Z57: 0.95260115 | AA57: -0.37342422 | AB57: 0.72414204 | AC57: -2.8044635 | AD57: 2.0930149 | AE57: -2.8044635 | AF57: 2.0930149
F58: Resultado | G58: =G56+G57=G55 -> TRUE | I58: Resíduos | J58: =F53-(J57+1) -> 5 | K58: =G57 -> 261907.24 | L58: =K58/J58 -> 52381.448
F59: R² | G59: =G56/G55 -> 0.39962369 | I59: Total | J59: =F53-1 -> 7 | K59: =G55 -> 436238.46 | L59: =K59/J59 -> 62319.78
F60: R² ajustado | G60: =1-(L58/L59) -> 0.15947316
F62: yTy | G62: 695391.07 | I62: LM | J62: =COUNTA(A41:A48)*G65 -> 3.1969895
F63: βTXTy | G63: 433483.83 | I63: χ² (crit) | J63: =CHIINV(5%,2) -> 5.9914645
F64: nYmédio² | G64: =H53 -> 259152.61
F65: R² aux | G65: =(G63-G64)/(G62-G64) -> 0.39962369 | I65: Não foi comprovado estatisticamente heterocedasticidade no modelo.
A69: Para o teste de White (TW) | X69: RESUMO DOS RESULTADOS
A70: ê^2 | C70: V(X1) | D70: K(X2) | E70: X1² | F70: X2² | G70: X1 x X2 | I70: 1 | J70: 1 | K70: 1 | L70: 1 | M70: 1 | N70: 1 | O70: 1 | P70: 1
A71: =F2 -> 15.479116 | B71: 1 | C71: =C2 -> 1170.6 | D71: =D2 -> 97.8 | E71: =C71^2 -> 1370304.4 | F71: =D71^2 -> 9564.84 | G71: =E71*F71 -> 1.3106742e+10 | I71: 1170.6 | J71: 1588 | K71: 1687.2 | L71: 1749.4 | M71: 1834.1 | N71: 2015.8 | O71: 2039.7 | P71: 2132.2 | X71: Estatística de regressão
A72: =F3 -> 58.114844 | B72: 1 | C72: =C3 -> 1588 | D72: =D3 -> 287.8 | E72: =C72^2 -> 2521744 | F72: =D72^2 -> 82828.84 | G72: =E72*F72 -> 2.0887313e+11 | I72: 97.8 | J72: 287.8 | K72: 321.3 | L72: 319.9 | M72: 220.9 | N72: 104.4 | O72: 156.2 | P72: 186.6 | X72: R múltiplo | Y72: 0.98056266
A73: =F4 -> 188.30633 | B73: 1 | C73: =C4 -> 1687.2 | D73: =D4 -> 321.3 | E73: =C73^2 -> 2846643.8 | F73: =D73^2 -> 103233.69 | G73: =E73*F73 -> 2.9386955e+11 | I73: 1370304.4 | J73: 2521744 | K73: 2846643.8 | L73: 3060400.4 | M73: 3363922.8 | N73: 4063449.6 | O73: 4160376.1 | P73: 4546276.8 | X73: R-Quadrado | Y73: 0.96150312
A74: =F5 -> 0.066240431 | B74: 1 | C74: =C5 -> 1749.4 | D74: =D5 -> 319.9 | E74: =C74^2 -> 3060400.4 | F74: =D74^2 -> 102336.01 | G74: =E74*F74 -> 3.1318916e+11 | I74: 9564.84 | J74: 82828.84 | K74: 103233.69 | L74: 102336.01 | M74: 48796.81 | N74: 10899.36 | O74: 24398.44 | P74: 34819.56 | X74: R-quadrado ajustado | Y74: 0.86526093
A75: =F6 -> 13.52914 | B75: 1 | C75: =C6 -> 1834.1 | D75: =D6 -> 220.9 | E75: =C75^2 -> 3363922.8 | F75: =D75^2 -> 48796.81 | G75: =E75*F75 -> 1.641487e+11 | I75: 1.3106742e+10 | J75: 2.0887313e+11 | K75: 2.9386955e+11 | L75: 3.1318916e+11 | M75: 1.641487e+11 | N75: 4.4289e+10 | O75: 1.0150669e+11 | P75: 1.5829936e+11 | X75: Erro padrão | Y75: 91.634651
A76: =F7 -> 85.595684 | B76: 1 | C76: =C7 -> 2015.8 | D76: =D7 -> 104.4 | E76: =C76^2 -> 4063449.6 | F76: =D76^2 -> 10899.36 | G76: =E76*F76 -> 4.4289e+10 | X76: Observações | Y76: 8
A77: =F8 -> 356.46055 | B77: 1 | C77: =C8 -> 2039.7 | D77: =D8 -> 156.2 | E77: =C77^2 -> 4160376.1 | F77: =D77^2 -> 24398.44 | G77: =E77*F77 -> 1.0150669e+11 | I77: {=MMULT(I70:P75,B71:G78)} -> 8 | J77: 14217 | K77: 1694.9 | L77: 25933118 | M77: 416877.55 | N77: 1.2972823e+12 | P77: {=MINVERSE(I77:N82)} -> 442.70884 | Q77: -0.61129229 | R77: 0.083562834 | S77: 0.00019181743 | T77: 0.0012091245 | U77: -3.6232658e-10
A78: =F9 -> 722.31647 | B78: 1 | C78: =C9 -> 2132.2 | D78: =D9 -> 186.6 | E78: =C78^2 -> 4546276.8 | F78: =D78^2 -> 34819.56 | G78: =E78*F78 -> 1.5829936e+11 | I78: 14217 | J78: 25933118 | K78: 3005313.4 | L78: 4.8305693e+10 | M78: 7.3140822e+08 | N78: 2.3256551e+15 | P78: -0.61129229 | Q78: 0.00086636111 | R78: -0.00026063912 | S78: -2.7300252e-07 | T78: -1.5780256e-06 | U78: 5.8020496e-13 | X78: ANOVA
I79: 1694.9 | J79: 3005313.4 | K79: 416877.55 | L79: 5.4189231e+09 | M79: 1.1290533e+08 | N79: 3.4228325e+14 | P79: 0.083562834 | Q79: -0.00026063912 | R79: 0.0014083394 | S79: 7.7166196e-08 | T79: -2.0918168e-06 | U79: -3.6932549e-13 | Y79: gl | Z79: SQ | AA79: MQ | AB79: F | AC79: F de significação
I80: 25933118 | J80: 4.8305693e+10 | K80: 5.4189231e+09 | L80: 9.151132e+13 | M80: 1.2972823e+12 | N80: 4.2138393e+18 | P80: 0.00019181743 | Q80: -2.7300252e-07 | R80: 7.7166196e-08 | S80: 8.646486e-11 | T80: 5.440341e-10 | U80: -1.9513917e-16 | X80: Regressão | Y80: 5 | Z80: 419444.64 | AA80: 83888.928 | AB80: 9.9904531 | AC80: 0.093481342
I81: 416877.55 | J81: 7.3140822e+08 | K81: 1.1290533e+08 | L81: 1.2972823e+12 | M81: 3.2389567e+10 | N81: 9.6295024e+16 | P81: 0.0012091245 | Q81: -1.5780256e-06 | R81: -2.0918168e-06 | S81: 5.440341e-10 | T81: 1.2680165e-08 | U81: -2.3798695e-15 | X81: Resíduo | Y81: 2 | Z81: 16793.819 | AA81: 8396.9093
I82: 1.2972823e+12 | J82: 2.3256551e+15 | K82: 3.4228325e+14 | L82: 4.2138393e+18 | M82: 9.6295024e+16 | N82: 2.9251514e+23 | P82: -3.6232658e-10 | Q82: 5.8020496e-13 | R82: -3.6932549e-13 | S82: -1.9513917e-16 | T82: -2.3798695e-15 | U82: 1.024056e-21 | X82: Total | Y82: 7 | Z82: 436238.46
I84: {=MMULT(I70:P75,A71:A78)} -> 1439.8684 | J84: 1439.8684 | K84: 1439.8684 | L84: 1439.8684 | M84: 1439.8684 | N84: 1439.8684 | P84: α | Q84: {=MMULT(P77:U82,I84:N89)} -> 8570.4433 | Y84: Coeficientes | Z84: Erro padrão | AA84: Stat t | AB84: valor-P | AC84: 95% inferiores | AD84: 95% superiores | AE84: Inferior 95,0% | AF84: Superior 95,0%
A85: Conclusão : Apesar da análise gráfica apresentar indicação de heterocedasticidade, estatisticamente não foi confirmado. | I85: 2892785.9 | J85: 2892785.9 | K85: 2892785.9 | L85: 2892785.9 | M85: 2892785.9 | N85: 2892785.9 | P85: β1 | Q85: -12.54102 | X85: Interseção | Y85: 8570.4433 | Z85: 1928.0524 | AA85: 4.4451299 | AB85: 0.04706518 | AC85: 274.70343 | AD85: 16866.183 | AE85: 274.70343 | AF85: 16866.183
I86: 281151.49 | J86: 281151.49 | K86: 281151.49 | L86: 281151.49 | M86: 281151.49 | N86: 281151.49 | P86: β2 | Q86: 6.811007 | X86: V(X1) | Y86: -12.54102 | Z86: 2.6971755 | AA86: -4.6496863 | AB86: 0.043274073 | AC86: -24.14603 | AD86: -0.93601052 | AE86: -24.14603 | AF86: -0.93601052
I87: 5.8641909e+09 | J87: 5.8641909e+09 | K87: 5.8641909e+09 | L87: 5.8641909e+09 | M87: 5.8641909e+09 | N87: 5.8641909e+09 | P87: β3 | Q87: 0.0039983105 | X87: K(X2) | Y87: 6.811007 | Z87: 3.4388513 | AA87: 1.9806053 | AB87: 0.18616849 | AC87: -7.9851759 | AD87: 21.60719 | AE87: -7.9851759 | AF87: 21.60719
I88: 59848916 | J88: 59848916 | K88: 59848916 | L88: 59848916 | M88: 59848916 | N88: 59848916 | P88: β4 | Q88: 0.0035321337 | X88: X1² | Y88: 0.0039983105 | Z88: 0.00085207839 | AA88: 4.6924209 | AB88: 0.042538804 | AC88: 0.00033211304 | AD88: 0.0076645079 | AE88: 0.00033211304 | AF88: 0.0076645079
I89: 2.2423685e+14 | J89: 2.2423685e+14 | K89: 2.2423685e+14 | L89: 2.2423685e+14 | M89: 2.2423685e+14 | N89: 2.2423685e+14 | P89: β5 | Q89: -4.2651437e-09 | X89: X2² | Y89: 0.0035321337 | Z89: 0.010318633 | AA89: 0.34230634 | AB89: 0.76474617 | AC89: -0.040865363 | AD89: 0.04792963 | AE89: -0.040865363 | AF89: 0.04792963
X90: X1 x X2 | Y90: -4.2651437e-09 | Z90: 2.9323889e-09 | AA90: -1.4544945 | AB90: 0.28303505 | AC90: -1.6882195e-08 | AD90: 8.3519076e-09 | AE90: -1.6882195e-08 | AF90: 8.3519076e-09
I91: STQ | J91: =O92-L92*M92^2 -> 436238.46 | L91: n | M91: ybarra | O91: yTy | P91: βTXTy | R91: LM | S91: =COUNTA(A71:A78)*J93 -> 7.692025
I92: SQReg | J92: =P92-L92*M92^2 -> 419444.64 | L92: =COUNT(D71:D78) -> 8 | M92: =AVERAGE(A71:A78) -> 179.98355 | O92: {=MMULT(TRANSPOSE(A71:A78),A71:A78)} -> 695391.07 | P92: {=MMULT(TRANSPOSE(Q84:Q89),MMULT(I70:P75,A71:A78))} -> 678597.25 | R92: χ² (crit) | S92: =CHIINV(5%,5) -> 11.070498 | U92: Não há comprovação de heterocedasticidade de acordo com o indicador.
I93: R² | J93: =J92/J91 -> 0.96150312
A96: PROCESSO DE CORREÇÃO DA HETEROCEDASTICIDADE POR MÍNIMOS QUADRADOS GENERALIZADOS FACTÍVEIS (MQGF)
A97: I(y) | C97: V(X1) | D97: K(X2) | E97: ê | F97: ln(ê²) | G97: v | L97: Matriz V | U97: (XTV-1X)-1
A98: 33.1 | B98: 1 | C98: 1170.6 | D98: 97.8 | E98: {=A98-($M$9+SUMPRODUCT(TRANSPOSE($M$10:$M$11),C98:D98))} -> 3.9343507 | F98: =LN(E98^2) -> 2.7394917 | G98: {=EXP($J$98)+SUMPRODUCT(TRANSPOSE($J$99:$J$100),C98:D98)} -> 3.9126753 | I98: γ | J98: =B123 -> 0.16090015 | L98: =G98 -> 3.9126753 | M98: 0 | N98: 0 | O98: 0 | P98: 0 | Q98: 0 | R98: 0 | S98: 0 | U98: {=MINVERSE(MMULT(H1:O3,MMULT(L109:S116,B2:D9)))} -> 23.704172 | V98: -0.011651711 | W98: -0.013455916
A99: 80 | B99: 1 | C99: 1588 | D99: 287.8 | E99: {=A99-($M$9+SUMPRODUCT(TRANSPOSE($M$10:$M$11),C99:D99))} -> 7.6233093 | F99: =LN(E99^2) -> 4.0624211 | G99: {=EXP($J$98)+SUMPRODUCT(TRANSPOSE($J$99:$J$100),C99:D99)} -> 3.144443 | I99: δ1 | J99: =B124 -> 0.0032786281 | L99: 0 | M99: =G99 -> 3.144443 | N99: 0 | O99: 0 | P99: 0 | Q99: 0 | R99: 0 | S99: 0 | U99: -0.011651711 | V99: 6.9800204e-06 | W99: -1.6181692e-06
A100: 67 | B100: 1 | C100: 1687.2 | D100: 321.3 | E100: {=A100-($M$9+SUMPRODUCT(TRANSPOSE($M$10:$M$11),C100:D100))} -> -13.722475 | F100: =LN(E100^2) -> 5.23807 | G100: {=EXP($J$98)+SUMPRODUCT(TRANSPOSE($J$99:$J$100),C100:D100)} -> 3.0929434 | I100: δ2 | J100: =B125 -> -0.011245956 | L100: 0 | M100: 0 | N100: =G100 -> 3.0929434 | O100: 0 | P100: 0 | Q100: 0 | R100: 0 | S100: 0 | U100: -0.013455916 | V100: -1.6181692e-06 | W100: 7.0450697e-05
A101: 82 | B101: 1 | C101: 1749.4 | D101: 319.9 | E101: {=A101-($M$9+SUMPRODUCT(TRANSPOSE($M$10:$M$11),C101:D101))} -> -0.25737217 | F101: =LN(E101^2) -> -2.7144643 | G101: {=EXP($J$98)+SUMPRODUCT(TRANSPOSE($J$99:$J$100),C101:D101)} -> 3.3126184 | L101: 0 | M101: 0 | N101: 0 | O101: =G101 -> 3.3126184 | P101: 0 | Q101: 0 | R101: 0 | S101: 0
A102: 72 | B102: 1 | C102: 1834.1 | D102: 220.9 | E102: {=A102-($M$9+SUMPRODUCT(TRANSPOSE($M$10:$M$11),C102:D102))} -> 3.6781979 | F102: =LN(E102^2) -> 2.6048459 | G102: {=EXP($J$98)+SUMPRODUCT(TRANSPOSE($J$99:$J$100),C102:D102)} -> 4.7036678 | L102: 0 | M102: 0 | N102: 0 | O102: 0 | P102: =G102 -> 4.7036678 | Q102: 0 | R102: 0 | S102: 0 | U102: (XTV-1y) | W102: Coeficientes corrigidos | Z102: O indicador com maior alteração foi o alfa. Os demais não houve mudança considerável.
A103: 45 | B103: 1 | C103: 2015.8 | D103: 104.4 | E103: {=A103-($M$9+SUMPRODUCT(TRANSPOSE($M$10:$M$11),C103:D103))} -> -9.2517936 | F103: =LN(E103^2) -> 4.4496349 | G103: {=EXP($J$98)+SUMPRODUCT(TRANSPOSE($J$99:$J$100),C103:D103)} -> 6.6095484 | L103: 0 | M103: 0 | N103: 0 | O103: 0 | P103: 0 | Q103: =G103 -> 6.6095484 | R103: 0 | S103: 0 | U103: {=MMULT(H1:O3,MMULT(L109:S116,A2:A9))} -> 125.89161 | W103: α | X103: {=MMULT(U98:W100,U103:U105)} -> -15.201318
A104: 44.6 | B104: 1 | C104: 2039.7 | D104: 156.2 | E104: {=A104-($M$9+SUMPRODUCT(TRANSPOSE($M$10:$M$11),C104:D104))} -> -18.880163 | F104: =LN(E104^2) -> 5.8762236 | G104: {=EXP($J$98)+SUMPRODUCT(TRANSPOSE($J$99:$J$100),C104:D104)} -> 6.1053671 | L104: 0 | M104: 0 | N104: 0 | O104: 0 | P104: 0 | Q104: 0 | R104: =G104 -> 6.1053671 | S104: 0 | U104: 221299.15 | W104: β1 | X104: 0.027210433
A105: 98 | B105: 1 | C105: 2132.2 | D105: 186.6 | E105: {=A105-($M$9+SUMPRODUCT(TRANSPOSE($M$10:$M$11),C105:D105))} -> 26.875946 | F105: =LN(E105^2) -> 6.5824634 | G105: {=EXP($J$98)+SUMPRODUCT(TRANSPOSE($J$99:$J$100),C105:D105)} -> 6.0667632 | L105: 0 | M105: 0 | N105: 0 | O105: 0 | P105: 0 | Q105: 0 | R105: 0 | S105: =G105 -> 6.0667632 | U105: 31275.76 | W105: β2 | X105: 0.15131265
A107: RESUMO DOS RESULTADOS | W107: Sigma^2
L108: Matriz V-1 | W108: yTy | X108: 37510.77
A109: Estatística de regressão | L109: {=MINVERSE(L98:S105)} -> 0.25557961 | M109: 0 | N109: 0 | O109: 0 | P109: 0 | Q109: 0 | R109: 0 | S109: 0 | W109: βTXTVtY | X109: {=MMULT(TRANSPOSE(X103:X105),U103:U105)} -> 8840.3455
A110: R múltiplo | B110: 0.50267191 | L110: 0 | M110: 0.31802135 | N110: 0 | O110: 0 | P110: 0 | Q110: 0 | R110: 0 | S110: 0 | W110: nYmédio² | X110: =COUNT(A98:A105)*AVERAGE(A98:A105)^2 -> 34021.361
A111: R-Quadrado | B111: 0.25267905 | L111: 0 | M111: 0 | N111: 0.32331662 | O111: 0 | P111: 0 | Q111: 0 | R111: 0 | S111: 0 | W111: SQRes | X111: =X108-X109 -> 28670.425
A112: R-quadrado ajustado | B112: -0.046249325 | L112: 0 | M112: 0 | N112: 0 | O112: 0.301876 | P112: 0 | Q112: 0 | R112: 0 | S112: 0
A113: Erro padrão | B113: 2.9770756 | L113: 0 | M113: 0 | N113: 0 | O113: 0 | P113: 0.21260005 | Q113: 0 | R113: 0 | S113: 0
A114: Observações | B114: 8 | L114: 0 | M114: 0 | N114: 0 | O114: 0 | P114: 0 | Q114: 0.15129627 | R114: 0 | S114: 0
L115: 0 | M115: 0 | N115: 0 | O115: 0 | P115: 0 | Q115: 0 | R115: 0.16379031 | S115: 0
A116: ANOVA | L116: 0 | M116: 0 | N116: 0 | O116: 0 | P116: 0 | Q116: 0 | R116: 0 | S116: 0.16483254
B117: gl | C117: SQ | D117: MQ | E117: F | F117: F de significação
A118: Regressão | B118: 2 | C118: 14.98345 | D118: 7.4917249 | E118: 0.84528292 | F118: 0.4828007
A119: Resíduo | B119: 5 | C119: 44.314896 | D119: 8.8629791
A120: Total | B120: 7 | C120: 59.298346 | L120: Em linhas gerais, concluí-se que não há heterocidasticidades entre as variáveis X e os processos de correção não serim necessários para este modelo.
B122: Coeficientes | C122: Erro padrão | D122: Stat t | E122: valor-P | F122: 95% inferiores | G122: 95% superiores | H122: Inferior 95,0% | I122: Superior 95,0%
A123: Interseção | B123: 0.16090015 | C123: 7.150845 | D123: 0.022500859 | E123: 0.98291878 | F123: -18.220932 | G123: 18.542732 | H123: -18.220932 | I123: 18.542732
A124: V(X1) | B124: 0.0032786281 | C124: 0.0036453924 | D124: 0.89938962 | E124: 0.40966664 | F124: -0.0060921514 | G124: 0.012649408 | H124: -0.0060921514 | I124: 0.012649408
A125: K(X2) | B125: -0.011245956 | C125: 0.012391167 | D125: -0.90757843 | E125: 0.405717 | F125: -0.043098465 | G125: 0.020606553 | H125: -0.043098465 | I125: 0.020606553

Sheet Questão 3 - Autocorrelação
B2: Insira seu nome e RA abaixo | D2: Escola Superior de Administração, Marketing e Comunicação (ESAMC) 10175/A - Econometria - 1º Sem. de 2021 - Prof. Pier Francesco De Maria | P2: Você recebeu os dados abaixo, necessários para construir uma função Cobb-Douglas para Taiwan, entre os anos de 1958 e 1972. Y é o produto real, L são os dias trabalhados e K é o volume de capital. Faça o que é pedido, na ordem.
B4: 101190648 | P4: 1) (1.00 pontos) Estime o modelo de regressão ln(Y) = α + β1ln(L) + β2ln(K) + e, por meio do método de MQO. Interprete os resultados.
D5: Prova 2 / Parte 3 (Autocorrelação serial) | P5: 2) (1.00 pontos) Construa a tabela ANOVA (e interprete o teste-F), calcule o R² ajustado e avalie a significância dos coeficientes (teste-T).
B6: Este exercício vale 17,5% (dezessete porcento e cinco décimos) da nota da P2. A nota desta prova será ponderada junto às demais notas da Prova 2, compondo a nota da P2. Faça o que é pedido, sempre utilizando (a não ser que seja solicitado o contrário) álgebra matricial. Deixe todas as fórmulas indicadas, sob pena de perder nota! Você recebeu essa prova em 07/05, durante a aula. Faça a QUESTÃO 3 e devolva-a até 28/05, antes do horário da aula (19h30). Ao terminar a sua prova, SALVE O ARQUIVO E ENVIE PARA O E-MAIL pier.francesco@esamc.br! | P6: 3) (1.50 pontos) Realize a avaliação gráfica e monte o correlograma; conclua se há ou não suspeita de autocorrelação serial.
P7: 4) (2.00 pontos) Realize o teste de regressores exógenos, bem como o teste Durbin-Watson. O que você conclui, a partir dos resultados?
P8: 5) (1.50 pontos) Realize o teste de Breusch-Godfrey para autocorrelação de 1ª e 2ª ordem. Analise os resultados.
P9: 6) (2.00 pontos) Aplique o método dos MQGF e obtenha os novos estimadores da regressão. Compare resultados com o item (1).
P10: 7) (1.00 pontos) O que você consegue concluir, diante das evidências encontradas?
P12: Ano | Q12: Y | R12: L | S12: K
P13: 1958 | Q13: 16607.7 | R13: 275.5 | S13: 17803.7
P14: 1959 | Q14: 17511.3 | R14: 274.4 | S14: 18096.8
P15: 1960 | Q15: 20171.2 | R15: 269.7 | S15: 18271.8
P16: 1961 | Q16: 20932.9 | R16: 267 | S16: 19167.3
P17: 1962 | Q17: 20406 | R17: 267.8 | S17: 19647.6
P18: 1963 | Q18: 20831.6 | R18: 275 | S18: 20803.5
P19: 1964 | Q19: 24806.3 | R19: 283 | S19: 22076.6
P20: 1965 | Q20: 26465.8 | R20: 300.7 | S20: 23445.2
P21: 1966 | Q21: 27403 | R21: 307.5 | S21: 24939
P22: 1967 | Q22: 28628.7 | R22: 303.7 | S22: 26713.7
P23: 1968 | Q23: 29904.5 | R23: 304.7 | S23: 29957.8
P24: 1969 | Q24: 27508.2 | R24: 298.6 | S24: 31585.9
... P27: 1972 | Q27: 31531.8 | R27: 288.1 | S27: 41794.3

Sheet RESOLUÇÃO QUESTÃO 3
A1: Ano | B1: Y | D1: L | E1: K | F1: ê | H1: 1 | I1: 1 | J1: 1 | K1: 1 | L1: 1 | M1: 1 | N1: 1 | O1: 1 | P1: 1 | Q1: 1 | R1: 1 | S1: 1 | T1: 1 | U1: 1 | V1: 1 | AA1: RESUMO DOS RESULTADOS
A2: 1958 | B2: 16607.7 | C2: 1 | D2: =LN('Questão 3 - Autocorrelação'!R13) -> 5.6185876 | E2: =LN('Questão 3 - Autocorrelação'!S13) -> 9.7871616 | F2: {=B2-($I$9+SUMPRODUCT(TRANSPOSE($I$10:$I$11),D2:E2))} -> -2853.5787 | H2: 5.6185876 | I2: 5.6145869 | J2: 5.5973102 | K2: 5.5872487 | L2: 5.5902404 | M2: 5.6167711 | N2: 5.6454469 | O2: 5.7061131 | P2: 5.7284751 | Q2: 5.7160404 | R2: 5.7193277 | S2: 5.6991049 | T2: 5.6886688 | U2: 5.7004436 | V2: 5.6633076
A3: 1959 | B3: 17511.3 | C3: 1 | D3: =LN('Questão 3 - Autocorrelação'!R14) -> 5.6145869 | E3: =LN('Questão 3 - Autocorrelação'!S14) -> 9.8034904 | F3: {=B3-($I$9+SUMPRODUCT(TRANSPOSE($I$10:$I$11),D3:E3))} -> -2012.3195 | H3: 9.7871616 | I3: 9.8034904 | J3: 9.8131142 | K3: 9.860961 | L3: 9.8857105 | M3: 9.9428765 | N3: 10.002274 | O3: 10.062421 | P3: 10.124188 | Q3: 10.192932 | R3: 10.307545 | S3: 10.360466 | T3: 10.418539 | U3: 10.457999 | V3: 10.640515 | AA3: Estatística de regressão
A4: 1960 | B4: 20171.2 | C4: 1 | D4: =LN('Questão 3 - Autocorrelação'!R15) -> 5.5973102 | E4: =LN('Questão 3 - Autocorrelação'!S15) -> 9.8131142 | F4: {=B4-($I$9+SUMPRODUCT(TRANSPOSE($I$10:$I$11),D4:E4))} -> 1112.423 | AA4: R múltiplo | AB4: 0.95370161
A5: 1961 | B5: 20932.9 | C5: 1 | D5: =LN('Questão 3 - Autocorrelação'!R16) -> 5.5872487 | E5: =LN('Questão 3 - Autocorrelação'!S16) -> 9.860961 | F5: {=B5-($I$9+SUMPRODUCT(TRANSPOSE($I$10:$I$11),D5:E5))} -> 1635.5937 | H5: {=MMULT(H1:V3,C2:E16)} -> 15 | I5: 84.891673 | J5: 151.66019 | L5: {=MINVERSE(H5:J7)} -> 1072.109 | M5: -225.24006 | N5: 20.047259 | P5: {=MMULT(H1:V3,B2:B16)} -> 371026 | Q5: 371026 | R5: 371026 | AA5: R-Quadrado | AB5: 0.90954676
A6: 1962 | B6: 20406 | C6: 1 | D6: =LN('Questão 3 - Autocorrelação'!R17) -> 5.5902404 | E6: =LN('Questão 3 - Autocorrelação'!S17) -> 9.8857105 | F6: {=B6-($I$9+SUMPRODUCT(TRANSPOSE($I$10:$I$11),D6:E6))} -> 709.7431 | H6: 84.891673 | I6: 480.47716 | J6: 858.45058 | L6: -225.24006 | M6: 52.065613 | N6: -6.8662453 | P6: 2102723.7 | Q6: 2102723.7 | R6: 2102723.7 | AA6: R-quadrado ajustado | AB6: 0.89447122
A7: 1963 | B7: 20831.6 | C7: 1 | D7: =LN('Questão 3 - Autocorrelação'!R18) -> 5.6167711 | E7: =LN('Questão 3 - Autocorrelação'!S18) -> 9.9428765 | F7: {=B7-($I$9+SUMPRODUCT(TRANSPOSE($I$10:$I$11),D7:E7))} -> -445.80354 | H7: 151.66019 | I7: 858.45058 | J7: 1534.4346 | L7: 20.047259 | M7: -6.8662453 | N7: 1.8605947 | P7: 3768589.4 | Q7: 3768589.4 | R7: 3768589.4 | AA7: Erro padrão | AB7: 1583.2552
A8: 1964 | B8: 24806.3 | C8: 1 | D8: =LN('Questão 3 - Autocorrelação'!R19) -> 5.6454469 | E8: =LN('Questão 3 - Autocorrelação'!S19) -> 10.002274 | F8: {=B8-($I$9+SUMPRODUCT(TRANSPOSE($I$10:$I$11),D8:E8))} -> 1848.7333 | AA8: Observações | AB8: 15
A9: 1965 | B9: 26465.8 | C9: 1 | D9: =LN('Questão 3 - Autocorrelação'!R20) -> 5.7061131 | E9: =LN('Questão 3 - Autocorrelação'!S20) -> 10.062421 | F9: {=B9-($I$9+SUMPRODUCT(TRANSPOSE($I$10:$I$11),D9:E9))} -> 743.47005 | H9: α | I9: {=MMULT(L5:N7,P5:R7)} -> -287429.42 | K9: ln(Y) = α + β1ln(L) + β2ln(K)
A10: 1966 | B10: 27403 | C10: 1 | D10: =LN('Questão 3 - Autocorrelação'!R21) -> 5.7284751 | E10: =LN('Questão 3 - Autocorrelação'!S21) -> 10.124188 | F10: {=B10-($I$9+SUMPRODUCT(TRANSPOSE($I$10:$I$11),D10:E10))} -> 184.21171 | H10: β1 | I10: 33621.085 | K10: A cada aumento de 1 dia em β1(dias trabalhados) aumenta 34.928,44 em Y (produto real) | AA10: ANOVA
A11: 1967 | B11: 28628.7 | C11: 1 | D11: =LN('Questão 3 - Autocorrelação'!R22) -> 5.7160404 | E11: =LN('Questão 3 - Autocorrelação'!S22) -> 10.192932 | F11: {=B11-($I$9+SUMPRODUCT(TRANSPOSE($I$10:$I$11),D11:E11))} -> 999.25077 | H11: β2 | I11: 12055.353 | K11: A cada aumento de 1 unidade em β1(volume de capital) aumenta 11.737,92 em Y (produto real) | AB11: gl | AC11: SQ | AD11: MQ | AE11: F | AF11: F de significação
A12: 1968 | B12: 29904.5 | C12: 1 | D12: =LN('Questão 3 - Autocorrelação'!R23) -> 5.7193277 | E12: =LN('Questão 3 - Autocorrelação'!S23) -> 10.307545 | F12: {=B12-($I$9+SUMPRODUCT(TRANSPOSE($I$10:$I$11),D12:E12))} -> 782.82532 | AA12: Regressão | AB12: 2 | AC12: 3.0247119e+08 | AD12: 1.5123559e+08 | AE12: 60.332615 | AF12: 5.4770259e-07
A13: 1969 | B13: 27508.2 | C13: 1 | D13: =LN('Questão 3 - Autocorrelação'!R24) -> 5.6991049 | E13: =LN('Questão 3 - Autocorrelação'!S24) -> 10.360466 | F13: {=B13-($I$9+SUMPRODUCT(TRANSPOSE($I$10:$I$11),D13:E13))} -> -1571.5446 | H13: n | I13: Ybarra | K13: yTy | L13: βTXTy | AA13: Resíduo | AB13: 12 | AC13: 30080366 | AD13: 2506697.1
A14: 1970 | B14: 29035.5 | C14: 1 | D14: =LN('Questão 3 - Autocorrelação'!R25) -> 5.6886688 | E14: =LN('Questão 3 - Autocorrelação'!S25) -> 10.418539 | F14: {=B14-($I$9+SUMPRODUCT(TRANSPOSE($I$10:$I$11),D14:E14))} -> -393.46553 | H14: =COUNT(B2:B16) -> 15 | I14: =AVERAGE(B2:B16) -> 24735.067 | K14: {=MMULT(TRANSPOSE(A2:A16),A2:A16)} -> 57918655 | L14: {=MMULT(TRANSPOSE(I9:I11),MMULT(H1:V3,A2:A16))} -> 7.2934951e+08 | AA14: Total | AB14: 14 | AC14: 3.3255155e+08
A15: 1971 | B15: 29281.5 | C15: 1 | D15: =LN('Questão 3 - Autocorrelação'!R26) -> 5.7004436 | E15: =LN('Questão 3 - Autocorrelação'!S26) -> 10.457999 | F15: {=B15-($I$9+SUMPRODUCT(TRANSPOSE($I$10:$I$11),D15:E15))} -> -1019.0452
A16: 1972 | B16: 31531.8 | C16: 1 | D16: =LN('Questão 3 - Autocorrelação'!R27) -> 5.6633076 | E16: =LN('Questão 3 - Autocorrelação'!S27) -> 10.640515 | F16: {=B16-($I$9+SUMPRODUCT(TRANSPOSE($I$10:$I$11),D16:E16))} -> 279.50617 | K16: STQ | L16: =K14-H14*I14^2 -> -9.1194342e+09 | N16: TABELA ANOVA | AB16: Coeficientes | AC16: Erro padrão | AD16: Stat t | AE16: valor-P | AF16: 95% inferiores | AG16: 95% superiores | AH16: Inferior 95,0% | AI16: Superior 95,0%
K17: SQReg | L17: =L14-H14*I14^2 -> -8.4480033e+09 | N17: Fonte | O17: GL | P17: SQ | Q17: QM | R17: F(calc) | S17: F(crit) | AA17: Interseção | AB17: -28075.862 | AC17: 9431.9216 | AD17: -2.9766852 | AE17: 0.011556722 | AF17: -48626.253 | AG17: -7525.4698 | AH17: -48626.253 | AI17: -7525.4698
K18: SQRes | L18: =K14-L14 -> -6.7143086e+08 | N18: Regressão | O18: 2 | P18: =L17 -> -8.4480033e+09 | Q18: =P18/O18 -> -4.2240017e+09 | R18: =Q18/Q19 -> 75.492539 | S18: =_xlfn.F.INV(5%,O18,O19) -> 0.051513171 | U18: O modelo é altamente significativo, segundo teste estatístico. | AA18: L | AB18: 147.97785 | AC18: 36.442878 | AD18: 4.0605424 | AE18: 0.001580168 | AF18: 68.57564 | AG18: 227.38006 | AH18: 68.57564 | AI18: 227.38006
K19: Resultado | L19: =L17+L18=L16 -> TRUE | N19: Resíduos | O19: =H14-(O18+1) -> 12 | P19: =L18 -> -6.7143086e+08 | Q19: =P19/O19 -> -55952571 | AA19: K | AB19: 0.40342393 | AC19: 0.073559385 | AD19: 5.4843299 | AE19: 0.00013972792 | AF19: 0.2431518 | AG19: 0.56369607 | AH19: 0.2431518 | AI19: 0.56369607
K20: R² | L20: =L17/L16 -> 0.92637363 | N20: Total | O20: =H14-1 -> 14 | P20: =L16 -> -9.1194342e+09 | Q20: =P20/O20 -> -6.5138816e+08
K21: R² ajustado | L21: =1-(Q19/Q20) -> 0.91410257
A34: Ano | B34: ê(t) | D34: ê(t-1) | E34: û(t)
A35: =A2 -> 1958 | B35: =F2 -> -2853.5787 | G35: 1 | H35: 1 | I35: 1 | J35: 1 | K35: 1 | L35: 1 | M35: 1 | N35: 1 | O35: 1 | P35: 1 | Q35: 1 | R35: 1 | S35: 1 | T35: 1 | AA35: RESUMO DOS RESULTADOS
A36: =A3 -> 1959 | B36: =F3 -> -2012.3195 | C36: 1 | D36: =B35 -> -2853.5787 | E36: =B36-$H$42*D36 -> -1204.5802 | G36: -2853.5787 | H36: -2012.3195 | I36: 1112.423 | J36: 1635.5937 | K36: 709.7431 | L36: -445.80354 | M36: 1848.7333 | N36: 743.47005 | O36: 184.21171 | P36: 999.25077 | Q36: 782.82532 | R36: -1571.5446 | S36: -393.46553 | T36: -1019.0452
A37: =A4 -> 1960 | B37: =F4 -> 1112.423 | C37: 1 | D37: =B36 -> -2012.3195 | E37: =B37-$H$42*D37 -> 1682.0338 | AA37: Estatística de regressão
A38: =A5 -> 1961 | B38: =F5 -> 1635.5937 | C38: 1 | D38: =B37 -> 1112.423 | E38: =B38-$H$42*D38 -> 1320.7092 | G38: {=MMULT(G35:T36,C36:D49)} -> 14 | H38: -279.50617 | J38: {=MINVERSE(G38:H39)} -> 0.071443854 | K38: 7.6549742e-07 | M38: {=MMULT(G35:T36,B36:B49)} -> 2853.5787 | N38: 2853.5787 | AA38: R múltiplo | AB38: 0.37718624
A39: =A6 -> 1962 | B39: =F6 -> 709.7431 | C39: 1 | D39: =B38 -> 1635.5937 | E39: =B39-$H$42*D39 -> 246.76894 | G39: -279.50617 | H39: 26086304 | J39: 7.6549742e-07 | K39: 3.8342495e-08 | M39: 7325486.7 | N39: 7325486.7 | AA39: R-Quadrado | AB39: 0.14226946
A40: =A7 -> 1963 | B40: =F7 -> -445.80354 | C40: 1 | D40: =B39 -> 709.7431 | E40: =B40-$H$42*D40 -> -646.70472 | AA40: R-quadrado ajustado | AB40: 0.065346382
A41: =A8 -> 1964 | B41: =F8 -> 1848.7333 | C41: 1 | D41: =B40 -> -445.80354 | E41: =B41-$H$42*D41 -> 1974.9233 | G41: α | H41: {=MMULT(J38:K39,M38:N39)} -> 209.4783 | J41: rho ^ | K41: {=SUMPRODUCT(B36:B49,D36:D49)/SUMPRODUCT(D36:D49,D36:D49)} -> 0.28081735 | AA41: Erro padrão | AB41: 1131.6192
A42: =A9 -> 1965 | B42: =F9 -> 743.47005 | C42: 1 | D42: =B41 -> 1848.7333 | E42: =B42-$H$42*D42 -> 220.16418 | G42: β1 | H42: 0.28306184 | J42: sigma² ^ | K42: {=SUMPRODUCT(E36:E49,E36:E49)/(H44-1)} -> 1228040.3 | AA42: Observações | AB42: 14
A43: =A10 -> 1966 | B43: =F10 -> 184.21171 | C43: 1 | D43: =B42 -> 743.47005 | E43: =B43-$H$42*D43 -> -26.236293 | J43: S(rho) | K43: {=SQRT(K42/SUMPRODUCT(D36:D49,D36:D49))} -> 0.21697017
A44: =A11 -> 1967 | B44: =F11 -> 999.25077 | C44: 1 | D44: =B43 -> 184.21171 | E44: =B44-$H$42*D44 -> 947.10746 | G44: n | H44: =COUNT(B36:B49) -> 14 | J44: t(calc) | K44: =K41/K43 -> 1.2942671 | M44: Não rejeita H0, pois o valor absoluto de t(calc) é menor do que o valor de t(crit). | AA44: ANOVA
A45: =A12 -> 1968 | B45: =F12 -> 782.82532 | C45: 1 | D45: =B44 -> 999.25077 | E45: =B45-$H$42*D45 -> 499.97556 | J45: t(crit) | K45: =TINV(5%,H44-1) -> 2.1603687 | AB45: gl | AC45: SQ | AD45: MQ | AE45: F | AF45: F de significação
A46: =A13 -> 1969 | B46: =F13 -> -1571.5446 | C46: 1 | D46: =B45 -> 782.82532 | E46: =B46-$H$42*D46 -> -1793.1326 | AA46: Regressão | AB46: 1 | AC46: 2761243.7 | AD46: 2761243.7 | AE46: 2.156275 | AF46: 0.16770806
A47: =A14 -> 1970 | B47: =F14 -> -393.46553 | C47: 1 | D47: =B46 -> -1571.5446 | E47: =B47-$H$42*D47 -> 51.378793 | AA47: Resíduo | AB47: 13 | AC47: 16647305 | AD47: 1280561.9
A48: =A15 -> 1971 | B48: =F15 -> -1019.0452 | C48: 1 | D48: =B47 -> -393.46553 | E48: =B48-$H$42*D48 -> -907.67016 | AA48: Total | AB48: 14 | AC48: 19408548
A49: =A16 -> 1972 | B49: =F16 -> 279.50617 | C49: 1 | D49: =B48 -> -1019.0452 | E49: =B49-$H$42*D49 -> 567.95899
AB50: Coeficientes | AC50: Erro padrão | AD50: Stat t | AE50: valor-P | AF50: 95% inferiores | AG50: 95% superiores | AH50: Inferior 95,0% | AI50: Superior 95,0%
AA51: Interseção | AB51: 0 | AC51: #N/A | AD51: #N/A | AE51: #N/A | AF51: #N/A | AG51: #N/A | AH51: #N/A | AI51: #N/A
AA52: Variável X 1 | AB52: 0.30304376 | AC52: 0.20637319 | AD52: 1.468426 | AE52: 0.16576597 | AF52: -0.1427984 | AG52: 0.74888592 | AH52: -0.1427984 | AI52: 0.74888592
A55: Teste Durbin-Watson
A56: rho ^ | B56: =K41 -> 0.28081735 | D56: Não rejeita hipótese nula.
A57: DM | B57: {=SUMSQ(B60:B73)/SUMSQ(B35:B49)} -> 1.1258357
A58: Ano | B58: ê(t) - ê(t-1)
A59: =A35 -> 1958
A60: =A36 -> 1959 | B60: =B36-D36 -> 841.25921
A61: =A37 -> 1960 | B61: =B37-D37 -> 3124.7424
A62: =A38 -> 1961 | B62: =B38-D38 -> 523.17072
A63: =A39 -> 1962 | B63: =B39-D39 -> -925.85058
A64: =A40 -> 1963 | B64: =B40-D40 -> -1155.5466
A65: =A41 -> 1964 | B65: =B41-D41 -> 2294.5369
A66: =A42 -> 1965 | B66: =B42-D42 -> -1105.2633
A67: =A43 -> 1966 | B67: =B43-D43 -> -559.25834
A68: =A44 -> 1967 | B68: =B44-D44 -> 815.03906
A69: =A45 -> 1968 | B69: =B45-D45 -> -216.42544
A70: =A46 -> 1969 | B70: =B46-D46 -> -2354.37
A71: =A47 -> 1970 | B71: =B47-D47 -> 1178.0791
... A73: =A49 -> 1972 | B73: =B49-D49 -> 1298.5514
A77: Teste Breusch-Godfrey | J77: RESUMO DOS RESULTADOS
B78: Y | E78: X1 | F78: X2 | G78: X3
A79: Ano | B79: ê(t) | C79: X1(t) | D79: X2(t) | E79: X1(t-1) | F79: X2(t-1) | G79: ê(t-1) | H79: ê(t-2) | J79: Estatística de regressão
A80: =A2 -> 1958 | B80: =F2 -> -2853.5787 | C80: =D2 -> 5.6185876 | D80: =E2 -> 9.7871616 | J80: R múltiplo | K80: 0.45218773
A81: =A3 -> 1959 | B81: =B36 -> -2012.3195 | C81: =D3 -> 5.6145869 | D81: =E3 -> 9.8034904 | E81: =C80 -> 5.6185876 | F81: =D80 -> 9.7871616 | G81: =B80 -> -2853.5787 | J81: R-Quadrado | K81: 0.20447374 | L81: LM | M81: =K81*(K84-1) -> 2.6581586 | O81: Não rejeita hipósete nula. Não há indícios de autocorrelação.
A82: =A4 -> 1960 | B82: =B37 -> 1112.423 | C82: =D4 -> 5.5973102 | D82: =E4 -> 9.8131142 | E82: =C81 -> 5.6145869 | F82: =D81 -> 9.8034904 | G82: =B81 -> -2012.3195 | H82: =B80 -> -2853.5787 | J82: R-quadrado ajustado | K82: -0.034184137 | L82: Chi²(crit) | M82: =CHIINV(5%,1) -> 3.8414588
A83: =A5 -> 1961 | B83: =B38 -> 1635.5937 | C83: =D5 -> 5.5872487 | D83: =E5 -> 9.860961 | E83: =C82 -> 5.5973102 | F83: =D82 -> 9.8131142 | G83: =B82 -> 1112.423 | H83: =B81 -> -2012.3195 | J83: Erro padrão | K83: 1177.8744
A84: =A6 -> 1962 | B84: =B39 -> 709.7431 | C84: =D6 -> 5.5902404 | D84: =E6 -> 9.8857105 | E84: =C83 -> 5.5872487 | F84: =D83 -> 9.860961 | G84: =B83 -> 1635.5937 | H84: =B82 -> 1112.423 | J84: Observações | K84: 14
A85: =A7 -> 1963 | B85: =B40 -> -445.80354 | C85: =D7 -> 5.6167711 | D85: =E7 -> 9.9428765 | E85: =C84 -> 5.5902404 | F85: =D84 -> 9.8857105 | G85: =B84 -> 709.7431 | H85: =B83 -> 1635.5937
A86: =A8 -> 1964 | B86: =B41 -> 1848.7333 | C86: =D8 -> 5.6454469 | D86: =E8 -> 10.002274 | E86: =C85 -> 5.6167711 | F86: =D85 -> 9.9428765 | G86: =B85 -> -445.80354 | H86: =B84 -> 709.7431 | J86: ANOVA
A87: =A9 -> 1965 | B87: =B42 -> 743.47005 | C87: =D9 -> 5.7061131 | D87: =E9 -> 10.062421 | E87: =C86 -> 5.6454469 | F87: =D86 -> 10.002274 | G87: =B86 -> 1848.7333 | H87: =B85 -> -445.80354 | K87: gl | L87: SQ | M87: MQ | N87: F | O87: F de significação
A88: =A10 -> 1966 | B88: =B43 -> 184.21171 | C88: =D10 -> 5.7284751 | D88: =E10 -> 10.124188 | E88: =C87 -> 5.7061131 | F88: =D87 -> 10.062421 | G88: =B87 -> 743.47005 | H88: =B86 -> 1848.7333 | J88: Regressão | K88: 3 | L88: 3565997.4 | M88: 1188665.8 | N88: 0.8567651 | O88: 0.49453115
A89: =A11 -> 1967 | B89: =B44 -> 999.25077 | C89: =D11 -> 5.7160404 | D89: =E11 -> 10.192932 | E89: =C88 -> 5.7284751 | F89: =D88 -> 10.124188 | G89: =B88 -> 184.21171 | H89: =B87 -> 743.47005 | J89: Resíduo | K89: 10 | L89: 13873882 | M89: 1387388.2
A90: =A12 -> 1968 | B90: =B45 -> 782.82532 | C90: =D12 -> 5.7193277 | D90: =E12 -> 10.307545 | E90: =C89 -> 5.7160404 | F90: =D89 -> 10.192932 | G90: =B89 -> 999.25077 | H90: =B88 -> 184.21171 | J90: Total | K90: 13 | L90: 17439879
A91: =A13 -> 1969 | B91: =B46 -> -1571.5446 | C91: =D13 -> 5.6991049 | D91: =E13 -> 10.360466 | E91: =C90 -> 5.7193277 | F91: =D90 -> 10.307545 | G91: =B90 -> 782.82532 | H91: =B89 -> 999.25077
A92: =A14 -> 1970 | B92: =B47 -> -393.46553 | C92: =D14 -> 5.6886688 | D92: =E14 -> 10.418539 | E92: =C91 -> 5.6991049 | F92: =D91 -> 10.360466 | G92: =B91 -> -1571.5446 | H92: =B90 -> 782.82532 | K92: Coeficientes | L92: Erro padrão | M92: Stat t | N92: valor-P | O92: 95% inferiores | P92: 95% superiores | Q92: Inferior 95,0% | R92: Superior 95,0%
A93: =A15 -> 1971 | B93: =B48 -> -1019.0452 | C93: =D15 -> 5.7004436 | D93: =E15 -> 10.457999 | E93: =C92 -> 5.6886688 | F93: =D92 -> 10.418539 | G93: =B92 -> -393.46553 | H93: =B91 -> -1571.5446 | J93: Interseção | K93: 12263.084 | L93: 42363.156 | M93: 0.28947521 | N93: 0.77813062 | O93: -82127.911 | P93: 106654.08 | Q93: -82127.911 | R93: 106654.08
A94: =A16 -> 1972 | B94: =B49 -> 279.50617 | C94: =D16 -> 5.6633076 | D94: =E16 -> 10.640515 | E94: =C93 -> 5.7004436 | F94: =D93 -> 10.457999 | G94: =B93 -> -1019.0452 | H94: =B92 -> -393.46553 | J94: Variável X 1 | K94: 550.59496 | L94: 10482.244 | M94: 0.052526439 | N94: 0.95914371 | O94: -22805.301 | P94: 23906.491 | Q94: -22805.301 | R94: 23906.491
J95: Variável X 2 | K95: -1506.0009 | L95: 2348.1761 | M95: -0.64134923 | N95: 0.53571788 | O95: -6738.0633 | P95: 3726.0615 | Q95: -6738.0633 | R95: 3726.0615
J96: Variável X 3 | K96: 0.27392403 | L96: 0.2310615 | M96: 1.1855027 | N96: 0.26322469 | O96: -0.24091307 | P96: 0.78876113 | Q96: -0.24091307 | R96: 0.78876113
A100: Correlograma
A101: Ano | B101: Y | F101: Lags | G101: rho | H101: IC (inf) | I101: IC (sup)
A102: =A2 -> 1958 | B102: =B2 -> 16607.7 | F102: 0 | G102: =(SUMPRODUCT(OFFSET($B$102:$B$116,+F102,0,$B$118-F102,1)-$B$119,OFFSET($B$102:$B$116,0,0,$B$118-F102,1)-$B$119)/$B$118)/$B$120 -> 1 | H102: =-I102 -> -0.50606052 | I102: =_xlfn.NORM.S.INV(1-5%/2)/SQRT($B$118) -> 0.50606052
A103: =A3 -> 1959 | B103: =B3 -> 17511.3 | F103: 1 | G103: =(SUMPRODUCT(OFFSET($B$102:$B$116,+F103,0,$B$118-F103,1)-$B$119,OFFSET($B$102:$B$116,0,0,$B$118-F103,1)-$B$119)/$B$118)/$B$120 -> 0.76403662 | H103: =-I103 -> -0.50606052 | I103: =_xlfn.NORM.S.INV(1-5%/2)/SQRT($B$118) -> 0.50606052
A104: =A4 -> 1960 | B104: =B4 -> 20171.2 | F104: 2 | G104: =(SUMPRODUCT(OFFSET($B$102:$B$116,+F104,0,$B$118-F104,1)-$B$119,OFFSET($B$102:$B$116,0,0,$B$118-F104,1)-$B$119)/$B$118)/$B$120 -> 0.56435937 | H104: =-I104 -> -0.74504483 | I104: =_xlfn.NORM.S.INV(1-5%/2)*SQRT((1+2*SUMSQ($G$103))/$B$118) -> 0.74504483
A105: =A5 -> 1961 | B105: =B5 -> 20932.9 | F105: 3 | G105: =(SUMPRODUCT(OFFSET($B$102:$B$116,+F105,0,$B$118-F105,1)-$B$119,OFFSET($B$102:$B$116,0,0,$B$118-F105,1)-$B$119)/$B$118)/$B$120 -> 0.41355701 | H105: =-I105 -> -0.74504483 | I105: =_xlfn.NORM.S.INV(1-5%/2)*SQRT((1+2*SUMSQ($G$103))/$B$118) -> 0.74504483
A106: =A6 -> 1962 | B106: =B6 -> 20406 | F106: 4 | G106: =(SUMPRODUCT(OFFSET($B$102:$B$116,+F106,0,$B$118-F106,1)-$B$119,OFFSET($B$102:$B$116,0,0,$B$118-F106,1)-$B$119)/$B$118)/$B$120 -> 0.29831809 | H106: =-I106 -> -0.74504483 | I106: =_xlfn.NORM.S.INV(1-5%/2)*SQRT((1+2*SUMSQ($G$103))/$B$118) -> 0.74504483
A107: =A7 -> 1963 | B107: =B7 -> 20831.6 | F107: 5 | G107: =(SUMPRODUCT(OFFSET($B$102:$B$116,+F107,0,$B$118-F107,1)-$B$119,OFFSET($B$102:$B$116,0,0,$B$118-F107,1)-$B$119)/$B$118)/$B$120 -> 0.067258958 | H107: =-I107 -> -0.74504483 | I107: =_xlfn.NORM.S.INV(1-5%/2)*SQRT((1+2*SUMSQ($G$103))/$B$118) -> 0.74504483
A108: =A8 -> 1964 | B108: =B8 -> 24806.3 | F108: 6 | G108: =(SUMPRODUCT(OFFSET($B$102:$B$116,+F108,0,$B$118-F108,1)-$B$119,OFFSET($B$102:$B$116,0,0,$B$118-F108,1)-$B$119)/$B$118)/$B$120 -> -0.14120251 | H108: =-I108 -> -0.74504483 | I108: =_xlfn.NORM.S.INV(1-5%/2)*SQRT((1+2*SUMSQ($G$103))/$B$118) -> 0.74504483
A109: =A9 -> 1965 | B109: =B9 -> 26465.8 | F109: 7 | G109: =(SUMPRODUCT(OFFSET($B$102:$B$116,+F109,0,$B$118-F109,1)-$B$119,OFFSET($B$102:$B$116,0,0,$B$118-F109,1)-$B$119)/$B$118)/$B$120 -> -0.26302205 | H109: =-I109 -> -0.74504483 | I109: =_xlfn.NORM.S.INV(1-5%/2)*SQRT((1+2*SUMSQ($G$103))/$B$118) -> 0.74504483
A110: =A10 -> 1966 | B110: =B10 -> 27403 | F110: 8 | G110: =(SUMPRODUCT(OFFSET($B$102:$B$116,+F110,0,$B$118-F110,1)-$B$119,OFFSET($B$102:$B$116,0,0,$B$118-F110,1)-$B$119)/$B$118)/$B$120 -> -0.36032323 | H110: =-I110 -> -0.74504483 | I110: =_xlfn.NORM.S.INV(1-5%/2)*SQRT((1+2*SUMSQ($G$103))/$B$118) -> 0.74504483
A111: =A11 -> 1967 | B111: =B11 -> 28628.7 | F111: 9 | G111: =(SUMPRODUCT(OFFSET($B$102:$B$116,+F111,0,$B$118-F111,1)-$B$119,OFFSET($B$102:$B$116,0,0,$B$118-F111,1)-$B$119)/$B$118)/$B$120 -> -0.43363976 | H111: =-I111 -> -0.74504483 | I111: =_xlfn.NORM.S.INV(1-5%/2)*SQRT((1+2*SUMSQ($G$103))/$B$118) -> 0.74504483
A112: =A12 -> 1968 | B112: =B12 -> 29904.5 | F112: 10 | G112: =(SUMPRODUCT(OFFSET($B$102:$B$116,+F112,0,$B$118-F112,1)-$B$119,OFFSET($B$102:$B$116,0,0,$B$118-F112,1)-$B$119)/$B$118)/$B$120 -> -0.38605371 | H112: =-I112 -> -0.74504483 | I112: =_xlfn.NORM.S.INV(1-5%/2)*SQRT((1+2*SUMSQ($G$103))/$B$118) -> 0.74504483
A113: =A13 -> 1969 | B113: =B13 -> 27508.2
A114: =A14 -> 1970 | B114: =B14 -> 29035.5
A115: =A15 -> 1971 | B115: =B15 -> 29281.5
A116: =A16 -> 1972 | B116: =B16 -> 31531.8
A118: Casos | B118: =COUNTA(B102:B116) -> 15
A119: Média | B119: =AVERAGE(B102:B116) -> 24735.067
A120: Variância | B120: =_xlfn.VAR.P(B102:B116) -> 22170103
A123: CORREÇÃO DO MODELO VIA MÍNIMOS QUADRADOS GENERALIZADOS FACTÍVEIS (MQGF)
B126: 1 | C126: 0.28081735 | D126: 0 | E126: 0 | F126: 0 | G126: 0 | H126: 0 | I126: 0 | J126: 0 | K126: 0 | L126: 0 | M126: 0 | N126: 0 | O126: 0 | P126: 0
...

Sheet Questão 4 - Variáveis Binárias
B2: Insira seu nome e RA abaixo | D2: Escola Superior de Administração, Marketing e Comunicação (ESAMC) 10175/A - Econometria - 1º Sem. de 2021 - Prof. Pier Francesco De Maria | P2: Você recebeu os dados abaixo, referentes ao salário de 15 professores (Y, em R$ mil por ano), anos de docência após concluir o doutorado (X) e universidade em que trabalha (D). Cuidado: você também sabe os nomes deles(as). Faça o que é pedido, na ordem.
B4: 101190648 | P4: USE APENAS O MÉTODO DIRETO! Cuidado, porém, para não esquecer de interpretar tudo (ANOVA, testes-T, coeficientes, R²...) nos itens (1) a (4)!
D5: Prova 2 / Parte 4 (Variáveis Binárias) | P5: 1) (1.50 pontos) Estime um modelo de regressão no qual você use as variáveis Y, X e D, sendo que D será "é ou não da Universidade A".
B6: Este exercício vale 17,5% (dezessete porcento e cinco décimos) da nota da P2. A nota desta prova será ponderada junto às demais notas da Prova 2, compondo a nota da P2. Faça o que é pedido, sempre utilizando (a não ser que seja solicitado o contrário) álgebra matricial. Deixe todas as fórmulas indicadas, sob pena de perder nota! Você recebeu essa prova em 01/06. Faça a QUESTÃO 4 e devolva-a até 11/06, antes do horário da aula (19h30). Ao terminar a sua prova, SALVE O ARQUIVO E ENVIE PARA O E-MAIL pier.francesco@esamc.br! | P6: 2) (2.00 pontos) Estime outro modelo de regressão, no qual você consiga observar o impacto de cada uma das universidades.
P7: 3) (2.00 pontos) Refaça o modelo do item (2), adicionando a variável sexo. O que aconteceu? Explique com suas palavras.
P8: 4) (1.50 pontos) Faça um modelo de regressão no qual haja uma quebra estrutural após os 20 anos de docência (X > 20).
P9: 5) (1.50 pontos) Existe quebra estrutural entre a universidade B e as demais? Teste isso e avalie os resultados.
P10: 6) (1.50 pontos) O que você consegue concluir, diante das evidências encontradas?
P12: Prof. | Q12: Y | R12: X | S12: D | T12: Z
P13: André | Q13: 105 | R13: 16 | S13: A | T13: Homem
P14: Paula | Q14: 98 | R14: 31 | S14: B | T14: Mulher
P15: Beto | Q15: 114 | R15: 15 | S15: A | T15: Homem
P16: Karol | Q16: 99 | R16: 21 | S16: C | T16: Mulher
P17: Caio | Q17: 93 | R17: 7 | S17: B | T17: Homem
P18: Julia | Q18: 46 | R18: 25 | S18: A | T18: Mulher
P19: Dênis | Q19: 73 | R19: 33 | S19: C | T19: Homem
P20: Pietra | Q20: 52 | R20: 10 | S20: B | T20: Mulher
P21: Rafael | Q21: 108 | R21: 16 | S21: A | T21: Homem
P22: Ticiana | Q22: 75 | R22: 40 | S22: C | T22: Mulher
P23: Flávio | Q23: 68 | R23: 18 | S23: C | T23: Homem
P24: Elisa | Q24: 121 | R24: 5 | S24: C | T24: Mulher
... P27: Bárbara | Q27: 72 | R27: 28 | S27: B | T27: Mulher

Sheet RESOLUÇÃO QUESTÃO 4
A1: Prof. | B1: Y | C1: X | D1: D(A=1) | E1: D(B=1) | F1: D(C=1) | H1: RESUMO DOS RESULTADOS | J1: Item 1
A2: André | B2: 105 | C2: 16 | D2: =IF('Questão 4 - Variáveis Binárias'!S13="A",1,0) -> 1 | E2: =IF('Questão 4 - Variáveis Binárias'!S13="B",1,0) -> 0 | F2: =IF('Questão 4 - Variáveis Binárias'!S13="C",1,0) -> 0
A3: Paula | B3: 98 | C3: 31 | D3: =IF('Questão 4 - Variáveis Binárias'!S14="A",1,0) -> 0 | E3: =IF('Questão 4 - Variáveis Binárias'!S14="B",1,0) -> 1 | F3: =IF('Questão 4 - Variáveis Binárias'!S14="C",1,0) -> 0 | H3: Estatística de regressão | M3: α | N3: β1 | O3: β2
A4: Beto | B4: 114 | C4: 15 | D4: =IF('Questão 4 - Variáveis Binárias'!S15="A",1,0) -> 1 | E4: =IF('Questão 4 - Variáveis Binárias'!S15="B",1,0) -> 0 | F4: =IF('Questão 4 - Variáveis Binárias'!S15="C",1,0) -> 0 | H4: R múltiplo | I4: 0.48614423 | L4: t(calc) | M4: =K17 -> 6.1987375 | N4: =K18 -> -1.5051583 | O4: =K19 -> 0.80804835 | P4: Rejeitamos H0 para todas as variáveis.
A5: Karol | B5: 99 | C5: 21 | D5: =IF('Questão 4 - Variáveis Binárias'!S16="A",1,0) -> 0 | E5: =IF('Questão 4 - Variáveis Binárias'!S16="B",1,0) -> 0 | F5: =IF('Questão 4 - Variáveis Binárias'!S16="C",1,0) -> 1 | H5: R-Quadrado | I5: 0.23633622 | L5: t(crit) | M5: =_xlfn.T.INV(5%,I13) -> -1.7822876
A6: Caio | B6: 93 | C6: 7 | D6: =IF('Questão 4 - Variáveis Binárias'!S17="A",1,0) -> 0 | E6: =IF('Questão 4 - Variáveis Binárias'!S17="B",1,0) -> 1 | F6: =IF('Questão 4 - Variáveis Binárias'!S17="C",1,0) -> 0 | H6: R-quadrado ajustado | I6: 0.10905892
A7: Julia | B7: 46 | C7: 25 | D7: =IF('Questão 4 - Variáveis Binárias'!S18="A",1,0) -> 1 | E7: =IF('Questão 4 - Variáveis Binárias'!S18="B",1,0) -> 0 | F7: =IF('Questão 4 - Variáveis Binárias'!S18="C",1,0) -> 0 | H7: Erro padrão | I7: 27.308298
A8: Dênis | B8: 73 | C8: 33 | D8: =IF('Questão 4 - Variáveis Binárias'!S19="A",1,0) -> 0 | E8: =IF('Questão 4 - Variáveis Binárias'!S19="B",1,0) -> 0 | F8: =IF('Questão 4 - Variáveis Binárias'!S19="C",1,0) -> 1 | H8: Observações | I8: 15
A9: Pietra | B9: 52 | C9: 10 | D9: =IF('Questão 4 - Variáveis Binárias'!S20="A",1,0) -> 0 | E9: =IF('Questão 4 - Variáveis Binárias'!S20="B",1,0) -> 1 | F9: =IF('Questão 4 - Variáveis Binárias'!S20="C",1,0) -> 0
A10: Rafael | B10: 108 | C10: 16 | D10: =IF('Questão 4 - Variáveis Binárias'!S21="A",1,0) -> 1 | E10: =IF('Questão 4 - Variáveis Binárias'!S21="B",1,0) -> 0 | F10: =IF('Questão 4 - Variáveis Binárias'!S21="C",1,0) -> 0 | H10: ANOVA
A11: Ticiana | B11: 75 | C11: 40 | D11: =IF('Questão 4 - Variáveis Binárias'!S22="A",1,0) -> 0 | E11: =IF('Questão 4 - Variáveis Binárias'!S22="B",1,0) -> 0 | F11: =IF('Questão 4 - Variáveis Binárias'!S22="C",1,0) -> 1 | I11: gl | J11: SQ | K11: MQ | L11: F | M11: F de significação
A12: Flávio | B12: 68 | C12: 18 | D12: =IF('Questão 4 - Variáveis Binárias'!S23="A",1,0) -> 0 | E12: =IF('Questão 4 - Variáveis Binárias'!S23="B",1,0) -> 0 | F12: =IF('Questão 4 - Variáveis Binárias'!S23="C",1,0) -> 1 | H12: Regressão | I12: 2 | J12: 2769.4823 | K12: 1384.7412 | L12: 1.8568607 | M12: 0.19834131 | N12: Rejeitamos H0. O modelo é significativo.
A13: Elisa | B13: 121 | C13: 5 | D13: =IF('Questão 4 - Variáveis Binárias'!S24="A",1,0) -> 0 | E13: =IF('Questão 4 - Variáveis Binárias'!S24="B",1,0) -> 0 | F13: =IF('Questão 4 - Variáveis Binárias'!S24="C",1,0) -> 1 | H13: Resíduo | I13: 12 | J13: 8948.9177 | K13: 745.74314
A14: Marco | B14: 153 | C14: 9 | D14: =IF('Questão 4 - Variáveis Binárias'!S25="A",1,0) -> 1 | E14: =IF('Questão 4 - Variáveis Binárias'!S25="B",1,0) -> 0 | F14: =IF('Questão 4 - Variáveis Binárias'!S25="C",1,0) -> 0 | H14: Total | I14: 14 | J14: 11718.4
A15: Sara | B15: 121 | C15: 19 | D15: =IF('Questão 4 - Variáveis Binárias'!S26="A",1,0) -> 0 | E15: =IF('Questão 4 - Variáveis Binárias'!S26="B",1,0) -> 1 | F15: =IF('Questão 4 - Variáveis Binárias'!S26="C",1,0) -> 0
A16: Bárbara | B16: 72 | C16: 28 | D16: =IF('Questão 4 - Variáveis Binárias'!S27="A",1,0) -> 0 | E16: =IF('Questão 4 - Variáveis Binárias'!S27="B",1,0) -> 1 | F16: =IF('Questão 4 - Variáveis Binárias'!S27="C",1,0) -> 0 | I16: Coeficientes | J16: Erro padrão | K16: Stat t | L16: valor-P | M16: 95% inferiores | N16: 95% superiores | O16: Inferior 95,0% | P16: Superior 95,0%
H17: Interseção | I17: 110.73905 | J17: 17.864775 | K17: 6.1987375 | L17: 4.5952752e-05 | M17: 71.815052 | N17: 149.66306 | O17: 71.815052 | P17: 149.66306
H18: X | I18: -1.1103327 | J18: 0.73768501 | K18: -1.5051583 | L18: 0.158143 | M18: -2.7176103 | N18: 0.49694482 | O18: -2.7176103 | P18: 0.49694482
H19: D(A=1) | I19: 12.448336 | J19: 15.405435 | K19: 0.80804835 | L19: 0.43478935 | M19: -21.117223 | N19: 46.013895 | O19: -21.117223 | P19: 46.013895
H21: RESUMO DOS RESULTADOS | J21: Item 2
H23: Estatística de regressão | M23: α | N23: β1 | O23: β2 | P23: β3 | Q23: β4
H24: R múltiplo | I24: 0.49154306 | L24: t(calc) | M24: =K36 -> 6.9020054 | N24: =K37 -> -1.4723192 | O24: =K38 -> 65535 | P24: =K39 -> -0.81599016 | Q24: =K40 -> -0.5156194 | R24: Rejeitamos H0 para todas as variáveis.
H25: R-Quadrado | I25: 0.24161458 | L25: t(crit) | M25: =_xlfn.T.INV(5%,I32) -> -1.7958848
H26: R-quadrado ajustado | I26: -0.0561269
H27: Erro padrão | I27: 28.423844
H28: Observações | I28: 15
H29: ANOVA
I30: gl | J30: SQ | K30: MQ | L30: F | M30: F de significação
H31: Regressão | I31: 4 | J31: 2831.3363 | K31: 707.83407 | L31: 1.1681661 | M31: 0.38118938 | N31: Rejeitamos H0. O modelo é significativo.
H32: Resíduo | I32: 11 | J32: 8887.0637 | K32: 807.91488
H33: Total | I33: 15 | J33: 11718.4
I35: Coeficientes | J35: Erro padrão | K35: Stat t | L35: valor-P | M35: 95% inferiores | N35: 95% superiores | O35: Inferior 95,0% | P35: Superior 95,0%
H36: Interseção | I36: 123.84593 | J36: 17.943471 | K36: 6.9020054 | L36: 2.5807382e-05 | M36: 84.352618 | N36: 163.33924 | O36: 84.352618 | P36: 163.33924
H37: X | I37: -1.1509834 | J37: 0.78174854 | K37: -1.4723192 | L37: 0.16896047 | M37: -2.8716003 | N37: 0.56963357 | O37: -2.8716003 | P37: 0.56963357
H38: D(A=1) | I38: 0 | J38: 0 | K38: 65535 | L38: #NUM! | M38: 0 | N38: 0 | O38: 0 | P38: 0
H39: D(B=1) | I39: -14.777247 | J39: 18.109589 | K39: -0.81599016 | L39: #NUM! | M39: -54.636184 | N39: 25.08169 | O39: -54.636184 | P39: 25.08169
H40: D(C=1) | I40: -9.7129198 | J40: 18.837382 | K40: -0.5156194 | L40: 0.61632482 | M40: -51.173719 | N40: 31.747879 | O40: -51.173719 | P40: 31.747879
A43: Prof. | B43: Y | C43: X | D43: D(A=1) | E43: D(B=1) | F43: D(C=1) | G43: Z(Mulher = 1) | I43: RESUMO DOS RESULTADOS | K43: Item 3
A44: André | B44: 105 | C44: 16 | D44: 1 | E44: 0 | F44: 0 | G44: =IF('Questão 4 - Variáveis Binárias'!T13="Mulher",1,0) -> 0
A45: Paula | B45: 98 | C45: 31 | D45: 0 | E45: 1 | F45: 0 | G45: =IF('Questão 4 - Variáveis Binárias'!T14="Mulher",1,0) -> 1 | I45: Estatística de regressão | N45: α | O45: β1 | P45: β2 | Q45: β3 | R45: β4 | S45: β5
A46: Beto | B46: 114 | C46: 15 | D46: 1 | E46: 0 | F46: 0 | G46: =IF('Questão 4 - Variáveis Binárias'!T15="Mulher",1,0) -> 0 | I46: R múltiplo | J46: 0.49674384 | M46: t(calc) | N46: =L59 -> 4.8786105 | O46: =L60 -> -1.2838666 | P46: =L61 -> 0.5578168 | Q46: =L62 -> 65535 | R46: =L63 -> 0.19458344 | S46: =L64 -> -0.26122053 | T46: Rejeitamos H0.
A47: Karol | B47: 99 | C47: 21 | D47: 0 | E47: 0 | F47: 1 | G47: =IF('Questão 4 - Variáveis Binárias'!T16="Mulher",1,0) -> 1 | I47: R-Quadrado | J47: 0.24675444 | M47: t(crit) | N47: =_xlfn.T.INV(5%,J55) -> -1.8124611
A48: Caio | B48: 93 | C48: 7 | D48: 0 | E48: 1 | F48: 0 | G48: =IF('Questão 4 - Variáveis Binárias'!T17="Mulher",1,0) -> 0 | I48: R-quadrado ajustado | J48: -0.15454379
A49: Julia | B49: 46 | C49: 25 | D49: 1 | E49: 0 | F49: 0 | G49: =IF('Questão 4 - Variáveis Binárias'!T18="Mulher",1,0) -> 1 | I49: Erro padrão | J49: 29.709986
A50: Dênis | B50: 73 | C50: 33 | D50: 0 | E50: 0 | F50: 1 | G50: =IF('Questão 4 - Variáveis Binárias'!T19="Mulher",1,0) -> 0 | I50: Observações | J50: 15
A51: Pietra | B51: 52 | C51: 10 | D51: 0 | E51: 1 | F51: 0 | G51: =IF('Questão 4 - Variáveis Binárias'!T20="Mulher",1,0) -> 1
A52: Rafael | B52: 108 | C52: 16 | D52: 1 | E52: 0 | F52: 0 | G52: =IF('Questão 4 - Variáveis Binárias'!T21="Mulher",1,0) -> 0 | I52: ANOVA
A53: Ticiana | B53: 75 | C53: 40 | D53: 0 | E53: 0 | F53: 1 | G53: =IF('Questão 4 - Variáveis Binárias'!T22="Mulher",1,0) -> 1 | J53: gl | K53: SQ | L53: MQ | M53: F | N53: F de significação
A54: Flávio | B54: 68 | C54: 18 | D54: 0 | E54: 0 | F54: 1 | G54: =IF('Questão 4 - Variáveis Binárias'!T23="Mulher",1,0) -> 0 | I54: Regressão | J54: 5 | K54: 2891.5672 | L54: 578.31344 | M54: 0.81897076 | N54: 0.56557739 | O54: Rejeitamos H0. O modelo é significativo.
A55: Elisa | B55: 121 | C55: 5 | D55: 0 | E55: 0 | F55: 1 | G55: =IF('Questão 4 - Variáveis Binárias'!T24="Mulher",1,0) -> 1 | I55: Resíduo | J55: 10 | K55: 8826.8328 | L55: 882.68328
A56: Marco | B56: 153 | C56: 9 | D56: 1 | E56: 0 | F56: 0 | G56: =IF('Questão 4 - Variáveis Binárias'!T25="Mulher",1,0) -> 0 | I56: Total | J56: 15 | K56: 11718.4
A57: Sara | B57: 121 | C57: 19 | D57: 0 | E57: 1 | F57: 0 | G57: =IF('Questão 4 - Variáveis Binárias'!T26="Mulher",1,0) -> 1
A58: Bárbara | B58: 72 | C58: 28 | D58: 0 | E58: 1 | F58: 0 | G58: =IF('Questão 4 - Variáveis Binárias'!T27="Mulher",1,0) -> 1 | J58: Coeficientes | K58: Erro padrão | L58: Stat t | M58: valor-P | N58: 95% inferiores | O58: 95% superiores | P58: Inferior 95,0% | Q58: Superior 95,0%
I59: Interseção | J59: 111.77525 | K59: 22.911288 | L59: 4.8786105 | M59: 0.00064329252 | N59: 60.72572 | O59: 162.82478 | P59: 60.72572 | Q59: 162.82478
I60: X | J60: -1.0904484 | K60: 0.84934718 | L60: -1.2838666 | M60: 0.22813771 | N60: -2.9829119 | O60: 0.80201501 | P60: -2.9829119 | Q60: 0.80201501
I61: D(A=1) | J61: 12.054197 | K61: 21.609598 | L61: 0.5578168 | M61: 0.58923821 | N61: -36.094987 | O61: 60.203381 | P61: -36.094987 | Q61: 60.203381
I62: D(B=1) | J62: 0 | K62: 0 | L62: 65535 | M62: #NUM! | N62: 0 | O62: 0 | P62: 0 | Q62: 0
I63: D(C=1) | J63: 3.8337906 | K63: 19.702553 | L63: 0.19458344 | M63: #NUM! | N63: -40.066234 | O63: 47.733815 | P63: -40.066234 | Q63: 47.733815
I64: Z(Mulher = 1) | J64: -4.8209128 | K64: 18.455336 | L64: -0.26122053 | M64: 0.79922347 | N64: -45.941965 | O64: 36.300139 | P64: -45.941965 | Q64: 36.300139
A67: Prof. | B67: Y | C67: X >20 | D67: D(A=1) | E67: D(B=1) | F67: D(C=1) | G67: Z(Mulher = 1) | I67: RESUMO DOS RESULTADOS | K67: Item 4
A68: André | B68: 105 | C68: =IF('Questão 4 - Variáveis Binárias'!R13<20,'Questão 4 - Variáveis Binárias'!R13,20) -> 16 | D68: 1 | E68: 0 | F68: 0 | G68: 0
A69: Paula | B69: 98 | C69: =IF('Questão 4 - Variáveis Binárias'!R14<20,'Questão 4 - Variáveis Binárias'!R14,20) -> 20 | D69: 0 | E69: 1 | F69: 0 | G69: 1 | I69: Estatística de regressão | N69: α | O69: β1 | P69: β2 | Q69: β3 | R69: β4
A70: Beto | B70: 114 | C70: =IF('Questão 4 - Variáveis Binárias'!R15<20,'Questão 4 - Variáveis Binárias'!R15,20) -> 15 | D70: 1 | E70: 0 | F70: 0 | G70: 0 | I70: R múltiplo | J70: 0.48450831 | M70: t(calc) | N70: =L83 -> 5.3726149 | O70: =L84 -> -1.4316338 | P70: =L85 -> 65535 | Q70: =L86 -> -0.9967874 | R70: =L87 -> -0.83084938 | S70: Rejeitamos H0.
A71: Karol | B71: 99 | C71: =IF('Questão 4 - Variáveis Binárias'!R16<20,'Questão 4 - Variáveis Binárias'!R16,20) -> 20 | D71: 0 | E71: 0 | F71: 1 | G71: 1 | I71: R-Quadrado | J71: 0.2347483 | M71: t(crit) | N71: =_xlfn.T.INV(5%,J79) -> -1.7958848
A72: Caio | B72: 93 | C72: =IF('Questão 4 - Variáveis Binárias'!R17<20,'Questão 4 - Variáveis Binárias'!R17,20) -> 7 | D72: 0 | E72: 1 | F72: 0 | G72: 0 | I72: R-quadrado ajustado | J72: -0.064865799
A73: Julia | B73: 46 | C73: =IF('Questão 4 - Variáveis Binárias'!R18<20,'Questão 4 - Variáveis Binárias'!R18,20) -> 20 | D73: 1 | E73: 0 | F73: 0 | G73: 1 | I73: Erro padrão | J73: 28.552226
A74: Dênis | B74: 73 | C74: =IF('Questão 4 - Variáveis Binárias'!R19<20,'Questão 4 - Variáveis Binárias'!R19,20) -> 20 | D74: 0 | E74: 0 | F74: 1 | G74: 0 | I74: Observações | J74: 15
A75: Pietra | B75: 52 | C75: =IF('Questão 4 - Variáveis Binárias'!R20<20,'Questão 4 - Variáveis Binárias'!R20,20) -> 10 | D75: 0 | E75: 1 | F75: 0 | G75: 1
A76: Rafael | B76: 108 | C76: =IF('Questão 4 - Variáveis Binárias'!R21<20,'Questão 4 - Variáveis Binárias'!R21,20) -> 16 | D76: 1 | E76: 0 | F76: 0 | G76: 0 | I76: ANOVA
A77: Ticiana | B77: 75 | C77: =IF('Questão 4 - Variáveis Binárias'!R22<20,'Questão 4 - Variáveis Binárias'!R22,20) -> 20 | D77: 0 | E77: 0 | F77: 1 | G77: 1 | J77: gl | K77: SQ | L77: MQ | M77: F | N77: F de significação
A78: Flávio | B78: 68 | C78: =IF('Questão 4 - Variáveis Binárias'!R23<20,'Questão 4 - Variáveis Binárias'!R23,20) -> 18 | D78: 0 | E78: 0 | F78: 1 | G78: 0 | I78: Regressão | J78: 4 | K78: 2750.8745 | L78: 687.71862 | M78: 1.1247852 | N78: 0.39818749 | O78: Rejeitamos H0. O modelo é significativo.
A79: Elisa | B79: 121 | C79: =IF('Questão 4 - Variáveis Binárias'!R24<20,'Questão 4 - Variáveis Binárias'!R24,20) -> 5 | D79: 0 | E79: 0 | F79: 1 | G79: 1 | I79: Resíduo | J79: 11 | K79: 8967.5255 | L79: 815.22959
A80: Marco | B80: 153 | C80: =IF('Questão 4 - Variáveis Binárias'!R25<20,'Questão 4 - Variáveis Binárias'!R25,20) -> 9 | D80: 1 | E80: 0 | F80: 0 | G80: 0 | I80: Total | J80: 15 | K80: 11718.4
A81: Sara | B81: 121 | C81: =IF('Questão 4 - Variáveis Binárias'!R26<20,'Questão 4 - Variáveis Binárias'!R26,20) -> 19 | D81: 0 | E81: 1 | F81: 0 | G81: 1
A82: Bárbara | B82: 72 | C82: =IF('Questão 4 - Variáveis Binárias'!R27<20,'Questão 4 - Variáveis Binárias'!R27,20) -> 20 | D82: 0 | E82: 1 | F82: 0 | G82: 1 | J82: Coeficientes | K82: Erro padrão | L82: Stat t | M82: valor-P | N82: 95% inferiores | O82: 95% superiores | P82: Inferior 95,0% | Q82: Superior 95,0%
I83: Interseção | J83: 136.71029 | K83: 25.445763 | L83: 5.3726149 | M83: 0.0002258819 | N83: 80.70454 | O83: 192.71604 | P83: 80.70454 | Q83: 192.71604
I84: X >20 | J84: -2.0730453 | K84: 1.4480276 | L84: -1.4316338 | M84: 0.18004319 | N84: -5.2601325 | O84: 1.114042 | P84: -5.2601325 | Q84: 1.114042
I85: D(A=1) | J85: 0 | K85: 0 | L85: 65535 | M85: #NUM! | N85: 0 | O85: 0 | P85: 0 | Q85: 0
I86: D(B=1) | J86: -18 | K86: 18.058013 | L86: -0.9967874 | M86: #NUM! | N86: -57.745419 | O86: 21.745419 | P86: -57.745419 | Q86: 21.745419
I87: D(C=1) | J87: -15.097737 | K87: 18.171448 | L87: -0.83084938 | M87: 0.42372601 | N87: -55.092825 | O87: 24.897351 | P87: -55.092825 | Q87: 24.897351
A89: Item 5
A90: Com certeza há alguma anomalia nos modelos onde testamos a variável com a universidade A e B, pois os resultados são os mesmos, mas não saberia testar estatisticamente esta quebra estrutural. | I90: RESUMO DOS RESULTADOS
I92: Estatística de regressão | N92: α | O92: β1 | P92: β2 | Q92: β3 | R92: β4 | S92: β5
A93: Item 6 | I93: R múltiplo | J93: 0.49160294 | M93: t(calc) | N93: =L106 -> 5.1029513 | O93: =L107 -> -1.2531028 | P93: =L108 -> 65535 | Q93: =L109 -> -0.67131336 | R93: =L110 -> -0.64681035 | S93: =L111 -> -0.30219437 | T93: Rejeitamos H0 para todos.
A94: Doscentes mulheres têm salário 5% menor | I94: R-Quadrado | J94: 0.24167345 | M94: t(crit) | N94: =_xlfn.T.INV(5%,J102) -> -1.8124611
A95: Universidade A no último modelo há quebra estrutural | I95: R-quadrado ajustado | J95: -0.16165717
A96: Universidade B há redução no salário de 14% . | I96: Erro padrão | J96: 29.810022
A97: Universidade C há redução no salário de 13%. | I97: Observações | J97: 15
A98: No último modelo executado.
A99: Apenas no primeiro modelo o R² ajustado foi significativo, nos demais ele foi negativo. | I99: ANOVA
J100: gl | K100: SQ | L100: MQ | M100: F | N100: F de significação
I101: Regressão | J101: 5 | K101: 2832.0261 | L101: 566.40523 | M101: 0.79673278 | N101: 0.57848619 | O101: Rejeitamos H0. O modelo é significativo.
I102: Resíduo | J102: 10 | K102: 8886.3739 | L102: 888.63739
I103: Total | J103: 15 | K103: 11718.4
J105: Coeficientes | K105: Erro padrão | L105: Stat t | M105: valor-P | N105: 95% inferiores | O105: 95% superiores | P105: Inferior 95,0% | Q105: Superior 95,0%
I106: Interseção | J106: 136.04013 | K106: 26.659108 | L106: 5.1029513 | M106: 0.00046203256 | N106: 76.639938 | O106: 195.44033 | P106: 76.639938 | Q106: 195.44033
I107: X >20 | J107: -1.9558253 | K107: 1.5607861 | L107: -1.2531028 | M107: 0.23867603 | N107: -5.4334734 | O107: 1.5218227 | P107: -5.4334734 | Q107: 1.5218227
I108: D(A=1) | J108: 0 | K108: 0 | L108: 65535 | M108: #NUM! | N108: 0 | O108: 0 | P108: 0 | Q108: 0
I109: D(B=1) | J109: -14.665236 | K109: 21.845589 | L109: -0.67131336 | M109: #NUM! | N109: -63.340242 | O109: 34.00977 | P109: -63.340242 | Q109: 34.00977
I110: D(C=1) | J110: -13.038668 | K110: 20.15841 | L110: -0.64681035 | M110: 0.53231933 | N110: -57.954406 | O110: 31.877069 | P110: -57.954406 | Q110: 31.877069
...
